Workbook
Name Origin: OFFSET(#REF!, 0, 0, COUNTA(#REF!))
Name Origin: OFFSET(#REF!, 0, 0, COUNTA(#REF!))
Name Origin: OFFSET(#REF!, 0, 0, COUNTA(#REF!))
Name Origin: OFFSET(#REF!, 0, 0, COUNTA(#REF!))
Name Origin: OFFSET(#REF!, 0, 0, COUNTA(#REF!))
Name Origin: OFFSET(#REF!, 0, 0, COUNTA(#REF!))
Name Origin: OFFSET(#REF!, 0, 0, COUNTA(#REF!))
Name Origin: OFFSET(Tariff!$G$8:$G$510, 0, 0, COUNTA(Tariff!$G$8:$G$510))

Sheet Cover Page

Sheet Conditions
B1: Conditions | I1: Vanguard Logistics Import LCL Tariff
B3: General
B5: Rates are subject to additional Bunker/Fuel costs associated with IMO/MARPOL 2020 Low Sulphur Measures.
B6: All rates shown in this pricing schedule are in US dollars unless otherwise stated.
B7: Other origins that do not appear in this Pricing Schedule may be available upon request. Please check with your local branches
B8: Ocean Freight Rates quoted herein cover general cargo only and freight that does not exceed 5.7 meters in length & 2.2 meters in height, any freight exceeding this must be advised prior to the booking of the freight. (Excluding Japan origin. Refer to Overdimensional surcharge Condition).
B9: All rates quoted are on a depot to depot basis. Please note that there will be import charges at destination ports and export charges at origin ports.
B10: Rates covering cargo transhipped outside Australia are inclusive of all transhipment costs.
B11: All rates are charged on a revenue tonnage basis. Either per cbm, per 1000kgs or Minimum which ever is the greater revenue.
B12: Any shipment weighing above 5 metric tonne will be charged at high density weight ratio. This ratio varies and is available at time of booking.
B13: All business undertaken is subject to the Company's Standard Trading Conditions, which may limit or exclude the Company's liability and contain indemnities benefiting the Company, copies of which are available upon request.
B14: Subject to Penalty fees/ surcharges imposed by the Carrier for misdeclared and non-compliant cargo.
B15: Open Coload fee of USD50.00 per B/L applicable on all relevant shipments.
... B21: Emergency Fuel Surcharge - Subject to change with / without notice.
B23: Origins | C23: Service | D23: Amount w/m Minimum | E23: Cargo Received or Arrived On or After
B24: All USA Origins | C24: Direct | D24: USD 6 | E24: 16th April 2026
B25: USA Inland IPI Service additional | C25: Gateway | D25: USD 6 | E25: 16th April 2026
B26: Canada | C26: Direct | D26: USD 6 | E26: 16th March 2026
B27: All UK Origins | C27: Direct | D27: USD 6 | E27: 16th March 2026
B28: Europe | C28: Direct | D28: USD 8 | E28: 16th March 2026
B29: China, Hong Kong, Japan | C29: Direct | D29: USD 10 | E29: 16th March 2026
B30: New Zealand | C30: Direct | D30: USD 7 | E30: 30th March 2026
B31: Papua New Guinea | C31: Direct | D31: USD 20 | E31: 28th May 2026
B32: Singapore | C32: Direct | D32: USD 6 | E32: 16th March 2026
B33: Malaysia, Indonesia, Thailand, Vietnam | C33: via Singapore | D33: USD 9 | E33: 16th March 2026
B34: Philippines | C34: via Singapore | D34: USD 10 | E34: 16th March 2026
... B36: All other origins via Singapore | C36: via Singapore | D36: USD 16 | E36: 16th March 2026
B38: High Density
B39: A high-density surcharge will apply for all shipments of 5000 KGS or greater. For these shipments we will charge at a W/M ratio of 1000 KGS = 1.6M3. For example, a 7000 KGS / 6.5M3 shipment will be rated as 7 X 1.6 = 11.2 Rev Tons
B41: High Volume
B42: A High Volume Surcharge will apply as follows, for shipments with volume greater than 20 CBM : 20-25CBM - USD30W/M 25-30CBM - USD35W/M 30-35CBM - USD40W/M 35CBM and above - USD45W/M A High Volume Surcharge of USD 15 per W/M will apply for volumes exceeding 15 CBM via Asia
B44: Heavy Weight Surcharge
B45: The maximum weight acceptance per-shipper-per-shipment is 5 metric tons. Anything above 5 metric tons, high density weight ratio applies. Kindly contact your local Customer Service representative for applicable rate in case your shipment exceeds this limit.
B46: Individual packages of 2500 KGS or greater may be subject to a surcharge. This is available upon request.
B47: Shipments greater than 7000 KGS are subject to acceptance and we reserve the right to split over multiple containers / sailings or HBLs
B49: Heavy Weight Surcharge (China and Hong Kong)
B50: An overweight surcharge of USD5 / metric tonne applies for all shipments where 1000kgs > 1cbm
B52: Heavy Lift Surcharge (shipments via Singapore)
B53: Surcharge of USD$150.00 per B/L is applicable for cargo moving via Singapore with weight of more than 3 tonne per package.
... B66: The following countries have been categorised as target risk countries:
B68: · Albania | C68: · Bulgaria | D68: · Georgia | E68: · Liechtenstein | F68: · Portugal | G68: · Slovenia | H68: · United Kingdom*
B69: · Andorra | C69: · Canada | D69: · Germany | E69: · Luxemburg | F69: · Republic of Korea* | G69: · Spain
B70: · Armenia | C70: · China* | D70: · Greece | E70: · Macedonia | F70: · Republic of North Macedonia | G70: · Switzerland
B71: · Austria | C71: · Croatia | D71: · Hungary | E71: · Montenegro | F71: · Romania | G71: · Turkey
B72: · Azerbaijan | C72: · Czechia | D72: · Italy | E72: · Moldova | F72: · Russia | G72: · Ukraine
B73: · Belgium | C73: · France | D73: · Kazakhstan | E73: · Netherlands | F73: · Serbia | G73: · United States of America
B74: · Bosnia & Herzegovina | C74: · Japan* | D74: · Kosovo | E74: · Poland | F74: · Slovakia | G74: · Uzbekistan
B76: * Japan, China & Republic of Korea (heightened vessel surveillance will be the only measure applied).
B77: * United Kingdom, China, Japan & Republic of Korea have been declared as emerging risk countries for the BMSB Season and may be selected for random onshore inspection
B78: Vanguard Logistics will be offering offshore treatment at origin ex USA, Italy, Belgium. We can also arrange LCL treatment in Singapore, Italy and Belgium for cargo moving via Transhipment hub.
B79: Please refer to our separate communication about BMSB for the applicable costs
B81: USA
B82: THE CUSTOMER’S BOOKING OF CARGO AFTER RECEIVING THE TERMS OF THIS NRA OR NRA AMENDMENT CONSITITUES ACCEPTANCE OF THE RATES AND TERMS OF THIS NRA OR NRA AMENDMENT. Shipments in U.S. trade will be subject to the NRA Terms and Conditions, which can be found at http://www.vanguardlogistics.com/nra-terms. There are additional terms that may apply to your Shipment, including those terms that may apply by force of law. These include the terms and conditions of: any ocean bill of lading (including Vanguard's ocean Bills of Lading, which can be found at http://www.vanguardlogistics.com/bill-of-lading-TC, for transportation by Vanguard Logistics Services (USA), Inc Vanguard Logistics Services (Hong Kong) Limited dba Vanguard Logistics Services dba Vanguard (OTI# 019927); and Vanguard Logistics Services (Japan) Limited dba Vanguard Logistics Services dba Vanguard (OTI# 021711)) Tariffs (including, for Shipments in U.S. trade, the NRA Tariff Rules https://portal.vanguardlogistics.com/apps/tariff-rules/; standard trading conditions; and the terms and conditions of any other Providers. The order of precedence in the event of any conflict among the terms that apply to your Shipment is as follows: the NRA Terms and Conditions, ocean bills of lading, tariffs, this Agreement, standard terms and conditions and any Provider's terms and conditions, including Provider's bills of lading.

Sheet Routing Order
B1: Routing Order | H1: Vanguard Logistics Import LCL Tariff
B4: Enter Origin Port Here® | E4: Aarhus | H4: =VLOOKUP(E4,B44:I152,2,FALSE) -> Denmark
G7: Routing Order
C8: Date:
C9: Supplier:
C10: Contact:
C11: Address:
C12: City:
C13: Country:
C14: Phone:
C15: Email:
C17: Dear Sir / Madam,
C18: =CONCATENATE("We wish to advise that we have made special arrangements with Vanguard Logistics Group Australia for the handling of our ocean freight shipments from ",H4,".") -> We wish to advise that we have made special arrangements with Vanguard Logistics Group Australia for the handling of our ocean freight shipments from Denmark .
C19: Until further notice, please consign all future orders through the Vanguard Logistics Group office at:
C21: Agent Name: | E21: =VLOOKUP(E4,B44:I154,3,FALSE) -> Greencarrier
C22: Address: | E22: =VLOOKUP(E4,B44:I155,4,FALSE) -> Nyhavn 16, 2nd Floor DK-1051 Copenhagen K, Denmark
C23: Contact: | E23: =VLOOKUP(E4,B44:I155,5,FALSE) -> Janni Hartmann
C24: Phone: | E24: =VLOOKUP(E4,B44:I155,6,FALSE) -> +45 77330600
C25: Email: | E25: =VLOOKUP(E4,B44:I155,7,FALSE) -> export.gcc.se@greencarrier.com ; Janni.Hartmann@greencarrier.com
C28: Yours Faithfully,
C32: Signature | H32: Date
C34: Company:
C35: Contact:
C36: Address:
C37: City:
C38: Country:
C39: Phone:
B44: Port | C44: Country | D44: Company | E44: Address | F44: Contact | G44: Phone | H44: email
B46: Chittagong | C46: Bangladesh | D46: Vanguard Logistics Services | E46: Monjur Building (1st Floor), 67 Agrabad C/A Agrabad, Chattogram-4100, Bangladesh | F46: Mizanur Rahman Kanchan Shill | G46: +880 9638 88 55 77 | H46: mizanur.rahman@vanguardlogistics.com kanchan.shill@vanguardlogistics.com
B47: Antwerp | C47: Belgium | D47: Vanguard Logistics Services | E47: Romeynsweel 8, 2030, Antwerpen | F47: Eva Bervoets | G47: +32 3 543 1800 | H47: eva.bervoets​@vanguardlogistics.com
B48: Santos | C48: Brazil | D48: Vanguard Logistics Services | E48: Av. Ana Costa, 433 – Cj 93 and 94 Gonzaga CEP 11060-003 Santos - SP, Brazil | F48: Maria Pilar | G48: +55 13 3229 7000 | H48: maria.pilar​@vanguardlogistics.com
B49: Phnom Penh | C49: Cambodia | D49: Vanguard Logistics Services (Cambodia) Pte Ltd | E49: No 4, Street 242, Sangkat Beungprolit, Khan 7 Makara, Phnom Penh, Cambodia | F49: Mr Ly Uy Ly | G49: 855-11 828388 | H49: ly.uyly@vls-cambodia.com
B50: Sihanoukville | C50: Cambodia | D50: Vanguard Logistics Services (Cambodia) Pte Ltd | E50: No 4, Street 242, Sangkat Beungprolit, Khan 7 Makara, Phnom Penh, Cambodia | F50: Mr Ly Uy Ly | G50: 855-11 828388 | H50: ly.uyly@vls-cambodia.com
B51: Montreal | C51: Canada | D51: Vanguard Logistics Services | E51: 465 Rue St-Jean, #700 Montreal,QC Canada H2Y 2R6 | F51: Operations | G51: +1 438 260 1832 | H51: exports.ca@vanguardlogistics.com antoinette.de.rosa@vanguardlogistics.com
B52: Toronto | C52: Canada | D52: Vanguard Logistics Services | E52: 1450 Meyerside Drive, Suite 402 Mississauga, Ontario Canada L5T 2 N5 Toronto | F52: Operations / Ashima Mehta | G52: +1 905 234 1650 | H52: exports.ca@vanguardlogistics.com ashima.mehta@vanguardlogistics.com
B53: Vancouver | C53: Canada | D53: Vanguard Logistics Services | E53: 1450 Meyerside Drive, Suite 402 Mississauga, Ontario Canada L5T 2 N5 Toronto | F53: Ashima Mehta | G53: +1 905-234-1650 | H53: exports.ca@vanguardlogistics.com ashima.mehta​@vanguardlogistics.com
B54: Dalian | C54: China | D54: Vanguard Logistics Services | E54: 20 Yide Street, Zhongshan District, Dalian 116001, China | F54: Mavis Li | G54: +86 411 3986 7765 | H54: mavis.li@vanguardlogistics.com
B55: Foshan | C55: China | D55: Vanguard Logistics Services | E55: Room 2003-2008, Guidu Building, No. 3007 Chunfeng Rd., Shenzhen, 518002 China | F55: Aly Zhong | G55: 8675582316764 | H55: aly.zhong​@vanguardlogistics.com
B56: Fuzhou | C56: China | D56: Vanguard Logistics Services | E56: Room 1621-1622, 3rd Building, Dong Er Huan Thaihot Plaza 11 Hengyu Road, Jin’an District, Fuzhou, Fujian, China 350011 | F56: Jessie Huang | G56: 86-591-8781 0020 | H56: jessie.huang@vanguardlogistics.com
B57: Guangzhou | C57: China | D57: Vanguard Logistics Services (Zhuhai) Ltd. - Guangzhou Branch | E57: Room 2201-7 Baihui Plaza, No. 193 Zhongshan 5 Road, Yuexiu District, Guangzhou, P.R.China 510030 | F57: Apple Dong | G57: 86-20-8364 9686 | H57: apple.dong@vanguardlogistics.com
B58: Huangpu | C58: China | D58: Vanguard Logistics Services (Zhuhai) Ltd. - Guangzhou Branch | E58: Room 2201-7 Baihui Plaza, No. 193 Zhongshan 5 Road, Yuexiu District, Guangzhou, P.R.China 510030 | F58: Apple Dong | G58: 86-20-8364 9686 | H58: apple.dong@vanguardlogistics.com
B59: Jiangmen | C59: China | D59: Vanguard Logisitic Services (HK) Ltd | E59: 36/ F Vicwood Plaza, 199 Des Voeux Road Central, Hong Kong | F59: Helen Cheng | G59: 852 3477 0123 | H59: helen.cheng@vanguardlogistics.com
B60: Ningbo | C60: China | D60: Vanguard Logistics Services | E60: 16/F Huanhe Center Block 1 No 168 Anbo Road Jiangdong District, Ningbo | F60: Eileen Tang | G60: +86 574 2766 6088 | H60: eileen.tang@vanguardlogistics.com
B61: Qingdao | C61: China | D61: Vanguard Logistics Services | E61: Unit A, F-H, 25/F, China-R international Mansion 2 Shandong Road Qingdao, China 266071 | F61: Roicy Li | G61: 86-532-8667 6812 | H61: roicy.li​@vanguardlogistics.com
B62: Shanghai | C62: China | D62: Vanguard Logistics Services | E62: 36/F BM Tower 218 Wusong Road Shanghai, China 200080 | F62: Ms Yoyo Zhang | G62: +86 21 2603 6117 | H62: yoyo.zhang@vanguardlogistics.com
B63: Shekou | C63: China | D63: Vanguard Logistics Services | E63: Room 2003-2008, Guidu Building, No. 3007 Chunfeng Rd., Shenzhen, 518002 China | F63: Daisy Zhong | G63: +86 755 8231 6839 | H63: daisy.zhong​@vanguardlogistics.com
B64: Shenzhen | C64: China | D64: Vanguard Logistics Services | E64: Room 2003-2008, Guidu Building, No. 3007 Chunfeng Rd., Shenzhen, 518002 China | F64: Daisy Zhong | G64: +86 755 8231 6839 | H64: daisy.zhong​@vanguardlogistics.com
B65: Shunde | C65: China | D65: Vanguard Logistics Services | E65: Room 2003-2008, Guidu Building, No. 3007 Chunfeng Rd., Shenzhen, 518002 China | F65: Aly Zhong | G65: 8675582316764 | H65: aly.zhong​@vanguardlogistics.com
B66: Tianjin | C66: China | D66: Vanguard Logistics Services | E66: Room 20H 20th Floor Teda Building 256 Jie Fang South Road Tianjin 300042, China | F66: Jenny Sun | G66: +86 22 5995 9312 | H66: jenny.sun@vanguardlogistics.com
B67: Xiamen | C67: China | D67: Vanguard Logistics Services | E67: Room 3001 The Bank Centre No. 189 Xia He Road Xiamen, Fujian, China 361003 | F67: Maggie Tang | G67: 86-592-2688 678 | H67: maggie.tang@vanguardlogistics.com
B68: Xingang | C68: China | D68: Vanguard Logistics Services | E68: Room 20H 20th Floor Teda Building 256 Jie Fang South Road Tianjin 300042, China | F68: Jenny Sun | G68: +86 22 5995 9312 | H68: jenny.sun@vanguardlogistics.com
B69: Yantian | C69: China | D69: Vanguard Logistics Services | E69: Room 2003-2008, Guidu Building, No. 3007 Chunfeng Rd., Shenzhen, 518002 China | F69: Daisy Zhong | G69: +86 755 8231 6839 | H69: daisy.zhong@vanguardlogistics.com
B70: Zhongshan | C70: China | D70: Vanguard Logistics Services | E70: Room 1511, Lihe International Financial Center, 16 Zhongshan 3rd Road, Zhongshan, Guangdong, China 528403 | F70: Kay Ng | G70: 86-760-8866 8707 | H70: kay.ng@vanguardlogistics.com
B71: Zhuhai | C71: China | D71: Vanguard Logisitic Services (HK) Ltd | E71: Units 1-2 and 4, 5th Floor, Production and Processing Center #3 1 Software Park Road, Zhuhai City, Guangdong, China 519080 | F71: Helen Cheng | G71: 852 3477 0123 | H71: helen.cheng@vanguardlogistics.com
B72: Aarhus | C72: Denmark | D72: Greencarrier | E72: Nyhavn 16, 2nd Floor DK-1051 Copenhagen K, Denmark | F72: Janni Hartmann | G72: +45 77330600 | H72: export.gcc.se@greencarrier.com ; Janni.Hartmann@greencarrier.com
B73: Copenhagen | C73: Denmark | D73: Greencarrier | E73: Nyhavn 16, 2nd Floor DK-1051 Copenhagen K, Denmark | F73: Janni Hartmann | G73: +45 77330600 | H73: export.gcc.se@greencarrier.com ; Janni.Hartmann@greencarrier.com
B74: Lautoka | C74: Fiji | D74: Vanguard Logistics Services (Fiji) | E74: 8 Rose Place Vunato Industrial Sub Division Lautoka | F74: Rizuana Begam | G74: (679) 666 0565 | H74: rizuana.begam@vanguardlogistics.com
B75: Suva | C75: Fiji | D75: Vanguard Logistics Services (Fiji) | E75: Lot 1 Foster Road Walubay Suva, Fiji | F75: Sangeeta Singh | G75: (679) 3315286 | H75: sangeeta.singh@vanguardlogistics.com
B76: Helsinki | C76: Finland | D76: Greencarrier | E76: Läkkisepäntie 23 FI-00620 Helsinki, Finland | F76: Nicolas Myrén | G76: +358 400 272 655 | H76: export.gcc.fi@greencarrier.com ; Nicolas.Myren@greencarrier.com
B77: Le Havre | C77: France | D77: Vanguard Logistics Services | E77: Romeynsweel 8, 2030, Antwerpen | F77: Eva Bervoets | G77: +32 3 543 1800 | H77: eva.bervoets​@vanguardlogistics.com
... B85: Chennai | C85: India | D85: Vanguard Logistics Services | E85: Olympia Cyberspace, 5th Floor, Arulaiyammanpet 2nd Street, Guindy, Chennai - 600032 Tamil Nadu, India | F85: Ramya Thinakaran | G85: +91 -44-4023-6697 | H85: csv.inmaa@vanguardlogistics.com ramya.thinakaran​@vanguardlogistics.com
B86: Cochin | C86: India | D86: Vanguard Logistics Services | E86: Teepeeyem House, 2nd Floor, Naval Road, Willingdon Island, Cochin - 682 003. Kerala, India. | F86: Mr. Agustin Rockey/Anthony George | G86: 914842666258 | H86: ops.incok@vanguardlogistics.com augustine.rockey​@vanguardlogistics.com antony.george​@vanguardlogistics.com
B87: Coimbatore | C87: India | D87: Vanguard Logistics Services | E87: No. 34 B, Plot No.9 Muniasamypuram 2nd Street Kamaraj Salai,Tuticorn - 628 003, Tamil Nadu, India | F87: Mr. K.Marimuthu | G87: +91 461 422 6410 | H87: ops.intut@vanguardlogistics.com marimuthu.kandasamy​@vanguardlogistics.com
B88: Hyderabad | C88: India | D88: Vanguard Logistics Services | E88: Rama Mansion M No. 1-11-254/11/A Plot No. 4, Situated, Begumpet Hyderabad, India 500 016 | F88: Karthik Mula | G88: +91 40 27765241 | H88: Karthik.Mula​@vanguardlogistics.com
B89: Mumbai | C89: India | D89: Vanguard Logistics Services | E89: The Summit Business Bay M-001 Mezzanine Floor Andheri Kurla Rd Andheri (East), Mumbai 400 093 Maharashtra, India | F89: Sachin Parnerkar | G89: +91 22 4908 5000 | H89: ops.inbom@vanguardlogistics.com sachin.parnerkar​@vanguardlogistics.com
B90: New Delhi | C90: India | D90: Vanguard Logistics Services | E90: B-6/8, 1st Floor, Okhla Industrial Area, Phase-II, New Delhi - 110 020. India. | F90: Rajesh Dogra | G90: +91-11-30679603 | H90: ops.indel@vanguardlogistics.com
B91: Nhava Sheva | C91: India | D91: Vanguard Logistics Services | E91: The Summit Business Bay M-001 Mezzanine Floor Andheri Kurla Rd Andheri (East), Mumbai 400 093 Maharashtra, India | F91: Sachin Parnerkar | G91: +91 22 4908 5000 | H91: ops.inbom@vanguardlogistics.com sachin.parnerkar​@vanguardlogistics.com
B92: Tuticorin | C92: India | D92: Vanguard Logistics Services | E92: No. 34 B, Plot No.9 Muniasamypuram 2nd Street Kamaraj Salai,Tuticorn - 628 003, Tamil Nadu, India | F92: Mr. K.Marimuthu | G92: +91 461 422 6410 | H92: ops.intut@vanguardlogistics.com marimuthu.kandasamy​@vanguardlogistics.com
B93: Belawan | C93: Indonesia | D93: Vanguard Logistics Services Indonesia | E93: Gedung Bank Mandiri 4th Floor Jl. Imam Bonjol No 7, Medan 20112 Indonesia | F93: Ria MELATI | G93: +62 61 4148194 | H93: Blw_export@vanguardlogistics.com ria.melati​@vanguardlogistics.com
B94: Jakarta | C94: Indonesia | D94: Vanguard Logistics Services Indonesia | E94: Hayam Wuruk Plaza Tower, 7th Floor, Suite AB Jl. Hayam Wuruk No 108 Jakarta 11160 Indonesia | F94: Tri SURYANDARI | G94: +62 21 6280748 | H94: jkt_export@vanguardlogistics.com tri.suryandari​@vanguardlogistics.com
B95: Semarang | C95: Indonesia | D95: Vanguard Logistics Services Indonesia | E95: Gedung Griya Bina Artha 3rd Floor Jl Pemuda No. 142, Semarang 50132, Central Java, Indonesia | F95: Emi Sumiarsih | G95: +62 24 352 1886 | H95: Srg_export@vanguardlogistics.com emi.sumiarsih​@vanguardlogistics.com
B96: Surabaya | C96: Indonesia | D96: Vanguard Logistics Services Indonesia | E96: Sinar Mas land Plaza 6th Floor Room 6071 Jl. Pemuda No 60-70 Surabaya 60271, Indonesia | F96: Hanysa Agung | G96: +62 31 5347658 | H96: Sub_export@vanguardlogistics.com hanysa.agung​@vanguardlogistics.com
B97: Dublin | C97: Ireland | D97: Vanguard Logistics | E97: Vanguard Logistics Station House - Station Road Maldon, Essex, United Kingdom CM9 4 LQ | F97: Hannah Symons | G97: +44 16 2187 9200 | H97: hannah.symons@vanguardlogistics.com; ukexpcsu@vanguardlogistics.com
B98: Haifa | C98: Israel | D98: Joint Transport International Services Ltd | E98: Shtibel 4, Tel Aviv | F98: Adi Shwartz | G98: +972-3-6384689 | H98: Export@jti.co.il
... B150: Ho Chi Minh | C150: Vietnam | D150: Vanguard Logistics Services | E150: 5FL, Ha Do Building, No. 02 Hong Ha Street Ward 02, Tan Binh District, Ho Chi Minh City, Viet Nam | F150: Ms Trung Nguyen | G150: (84) 8 3845 9690 | H150: trung.nguyen@vanguardlogistics.com.vn,

Sheet IMO2020 Surcharges
B1: IMO2020 Surcharges | D1: Vanguard Logistics LCL Import Tariff
B4: IMO2020 Surcharge Validity | D4: 01 July 26 - 30 September 26
B5: Origin or Via Country / Region | D5: Currency | E5: Amount per w/m
B6: New Zealand | D6: USD | E6: 15
B7: Asia (excluding Korea & Taiwan) | D7: USD | E7: 3
B8: Korea - Sydney / Melbourne (Maxpeed Korea) | D8: USD | E8: 3
B9: Korea - Fremantle / Adelaide / Brisbane (Maxpeed Korea) | D9: USD | E9: 3
B10: Taiwan (Oriental Vanguard Logistics) | D10: USD | E10: 3
B11: Middle East and India Sub-Continent | D11: USD | E11: 0
B12: USA | D12: USD | E12: 6
B13: Israel (JTI Joint Transport International) | D13: USD | E13: 0
B14: Portugal (Allways Cargo) | D14: USD | E14: 0
B15: South Africa | D15: USD | E15: 5
B16: Rest Of World | D16: USD | E16: 0
B17: IMO2020 Surcharges are subject to change based on market fluctuations

Sheet Rate Search
B1: Rate Search | L1: Vanguard Logistics LCL Import Tariff
B4: Use this table to obtain an Import LCL rate
B7: Enter Origin Port Here ® | D7: Shanghai | H7: {=IFERROR(INDEX(Tariff!$B$7:$AA$554,MATCH($D$7,Tariff!$G$7:$G$554,0)+0,MATCH("Country",Tariff!$B$7:$AA$7,0)),"")} -> China | L7: =VLOOKUP(D7,Tariff!G7:J554,4,FALSE) -> CNSHG
C10: Rates | L10: Service Details
B11: Destination | C11: Currency | D11: Rate per cbm | E11: Rate per tonne | F11: Minimum Charge | G11: GRI per w/m | H11: PSS per w/m | I11: IMO2020 per w/m | J11: BAF/EFS per w/m | K11: ETS per w/m | L11: Service Type | M11: via Port | N11: Transit Time | O11: Frequency | P11: Validity
B12: {=IF($D$7=IFERROR(INDEX(Tariff!$B$7:$AA$554,MATCH($D$7,Tariff!$G$7:$G$554,0)+0,MATCH("Origin Port",Tariff!$B$7:$AA$7,0)),""),IFERROR(INDEX(Tariff!$B$7:$AA$554,MATCH($D$7,Tariff!$G$7:$G$554,0)+0,MATCH("Destination Port",Tariff!$B$7:$AA$7,0)),""),"")} -> Sydney | C12: {=IF($D$7=IFERROR(INDEX(Tariff!$B$7:$AA$554,MATCH($D$7,Tariff!$G$7:$G$554,0)+0,MATCH("Origin Port",Tariff!$B$7:$AA$7,0)),""),IFERROR(INDEX(Tariff!$B$7:$AA$554,MATCH($D$7,Tariff!$G$7:$G$554,0)+0,MATCH(C11,Tariff!$B$7:$AA$7,0)),""),"")} -> USD | D12: {=IF($D$7=IFERROR(INDEX(Tariff!$B$7:$AA$554,MATCH($D$7,Tariff!$G$7:$G$554,0)+0,MATCH("Origin Port",Tariff!$B$7:$AA$7,0)),""),IFERROR(INDEX(Tariff!$B$7:$AA$554,MATCH($D$7,Tariff!$G$7:$G$554,0)+0,MATCH(D11,Tariff!$B$7:$AA$7,0)),""),"")} -> 40 | E12: {=IF($D$7=IFERROR(INDEX(Tariff!$B$7:$AA$554,MATCH($D$7,Tariff!$G$7:$G$554,0)+0,MATCH("Origin Port",Tariff!$B$7:$AA$7,0)),""),IFERROR(INDEX(Tariff!$B$7:$AA$554,MATCH($D$7,Tariff!$G$7:$G$554,0)+0,MATCH(E11,Tariff!$B$7:$AA$7,0)),""),"")} -> 40 | F12: {=IF($D$7=IFERROR(INDEX(Tariff!$B$7:$AA$554,MATCH($D$7,Tariff!$G$7:$G$554,0)+0,MATCH("Origin Port",Tariff!$B$7:$AA$7,0)),""),IFERROR(INDEX(Tariff!$B$7:$AA$554,MATCH($D$7,Tariff!$G$7:$G$554,0)+0,MATCH(F11,Tariff!$B$7:$AA$7,0)),""),"")} -> 40 | G12: {=IF($D$7=IFERROR(INDEX(Tariff!$B$7:$AA$554,MATCH($D$7,Tariff!$G$7:$G$554,0)+0,MATCH("Origin Port",Tariff!$B$7:$AA$7,0)),""),IFERROR(INDEX(Tariff!$B$7:$AA$554,MATCH($D$7,Tariff!$G$7:$G$554,0)+0,MATCH(G11,Tariff!$B$7:$AA$7,0)),""),"")} -> N/A | H12: {=IF($D$7=IFERROR(INDEX(Tariff!$B$7:$AA$554,MATCH($D$7,Tariff!$G$7:$G$554,0)+0,MATCH("Origin Port",Tariff!$B$7:$AA$7,0)),""),IFERROR(INDEX(Tariff!$B$7:$AA$554,MATCH($D$7,Tariff!$G$7:$G$554,0)+0,MATCH(H11,Tariff!$B$7:$AA$7,0)),""),"")} -> N/A | I12: {=IF($D$7=IFERROR(INDEX(Tariff!$B$7:$AA$554,MATCH($D$7,Tariff!$G$7:$G$554,0)+0,MATCH("Origin Port",Tariff!$B$7:$AA$7,0)),""),IFERROR(INDEX(Tariff!$B$7:$AA$554,MATCH($D$7,Tariff!$G$7:$G$554,0)+0,MATCH(I11,Tariff!$B$7:$AA$7,0)),""),"")} -> 3 | J12: {=IF($D$7=IFERROR(INDEX(Tariff!$B$7:$AA$554,MATCH($D$7,Tariff!$G$7:$G$554,0)+0,MATCH("Origin Port",Tariff!$B$7:$AA$7,0)),""),IFERROR(INDEX(Tariff!$B$7:$AA$554,MATCH($D$7,Tariff!$G$7:$G$554,0)+0,MATCH(J11,Tariff!$B$7:$AA$7,0)),""),"")} -> 10 | ... P12: {=IF($D$7=IFERROR(INDEX(Tariff!$B$7:$AA$554,MATCH($D$7,Tariff!$G$7:$G$554,0)+0,MATCH("Origin Port",Tariff!$B$7:$AA$7,0)),""),IFERROR(INDEX(Tariff!$B$7:$AA$554,MATCH($D$7,Tariff!$G$7:$G$554,0)+0,MATCH(P11,Tariff!$B$7:$AA$7,0)),""),"")} -> 46265
B13: {=IF($D$7=IFERROR(INDEX(Tariff!$B$7:$AA$554,MATCH($D$7,Tariff!$G$7:$G$554,0)+1,MATCH("Origin Port",Tariff!$B$7:$AA$7,0)),""),IFERROR(INDEX(Tariff!$B$7:$AA$554,MATCH($D$7,Tariff!$G$7:$G$554,0)+1,MATCH("Destination Port",Tariff!$B$7:$AA$7,0)),""),"")} -> Melbourne | C13: {=IF($D$7=IFERROR(INDEX(Tariff!$B$7:$AA$554,MATCH($D$7,Tariff!$G$7:$G$554,0)+1,MATCH("Origin Port",Tariff!$B$7:$AA$7,0)),""),IFERROR(INDEX(Tariff!$B$7:$AA$554,MATCH($D$7,Tariff!$G$7:$G$554,0)+1,MATCH(C11,Tariff!$B$7:$AA$7,0)),""),"")} -> USD | D13: {=IF($D$7=IFERROR(INDEX(Tariff!$B$7:$AA$554,MATCH($D$7,Tariff!$G$7:$G$554,0)+1,MATCH("Origin Port",Tariff!$B$7:$AA$7,0)),""),IFERROR(INDEX(Tariff!$B$7:$AA$554,MATCH($D$7,Tariff!$G$7:$G$554,0)+1,MATCH(D11,Tariff!$B$7:$AA$7,0)),""),"")} -> 38 | E13: {=IF($D$7=IFERROR(INDEX(Tariff!$B$7:$AA$554,MATCH($D$7,Tariff!$G$7:$G$554,0)+1,MATCH("Origin Port",Tariff!$B$7:$AA$7,0)),""),IFERROR(INDEX(Tariff!$B$7:$AA$554,MATCH($D$7,Tariff!$G$7:$G$554,0)+1,MATCH(E11,Tariff!$B$7:$AA$7,0)),""),"")} -> 38 | F13: {=IF($D$7=IFERROR(INDEX(Tariff!$B$7:$AA$554,MATCH($D$7,Tariff!$G$7:$G$554,0)+1,MATCH("Origin Port",Tariff!$B$7:$AA$7,0)),""),IFERROR(INDEX(Tariff!$B$7:$AA$554,MATCH($D$7,Tariff!$G$7:$G$554,0)+1,MATCH(F11,Tariff!$B$7:$AA$7,0)),""),"")} -> 38 | G13: {=IF($D$7=IFERROR(INDEX(Tariff!$B$7:$AA$554,MATCH($D$7,Tariff!$G$7:$G$554,0)+1,MATCH("Origin Port",Tariff!$B$7:$AA$7,0)),""),IFERROR(INDEX(Tariff!$B$7:$AA$554,MATCH($D$7,Tariff!$G$7:$G$554,0)+1,MATCH(G11,Tariff!$B$7:$AA$7,0)),""),"")} -> N/A | H13: {=IF($D$7=IFERROR(INDEX(Tariff!$B$7:$AA$554,MATCH($D$7,Tariff!$G$7:$G$554,0)+1,MATCH("Origin Port",Tariff!$B$7:$AA$7,0)),""),IFERROR(INDEX(Tariff!$B$7:$AA$554,MATCH($D$7,Tariff!$G$7:$G$554,0)+1,MATCH(H11,Tariff!$B$7:$AA$7,0)),""),"")} -> N/A | I13: {=IF($D$7=IFERROR(INDEX(Tariff!$B$7:$AA$554,MATCH($D$7,Tariff!$G$7:$G$554,0)+1,MATCH("Origin Port",Tariff!$B$7:$AA$7,0)),""),IFERROR(INDEX(Tariff!$B$7:$AA$554,MATCH($D$7,Tariff!$G$7:$G$554,0)+1,MATCH(I11,Tariff!$B$7:$AA$7,0)),""),"")} -> 3 | J13: {=IF($D$7=IFERROR(INDEX(Tariff!$B$7:$AA$554,MATCH($D$7,Tariff!$G$7:$G$554,0)+1,MATCH("Origin Port",Tariff!$B$7:$AA$7,0)),""),IFERROR(INDEX(Tariff!$B$7:$AA$554,MATCH($D$7,Tariff!$G$7:$G$554,0)+1,MATCH(J11,Tariff!$B$7:$AA$7,0)),""),"")} -> 10 | ... P13: {=IF($D$7=IFERROR(INDEX(Tariff!$B$7:$AA$554,MATCH($D$7,Tariff!$G$7:$G$554,0)+1,MATCH("Origin Port",Tariff!$B$7:$AA$7,0)),""),IFERROR(INDEX(Tariff!$B$7:$AA$554,MATCH($D$7,Tariff!$G$7:$G$554,0)+1,MATCH(P11,Tariff!$B$7:$AA$7,0)),""),"")} -> 46265
B14: {=IF($D$7=IFERROR(INDEX(Tariff!$B$7:$AA$554,MATCH($D$7,Tariff!$G$7:$G$554,0)+2,MATCH("Origin Port",Tariff!$B$7:$AA$7,0)),""),IFERROR(INDEX(Tariff!$B$7:$AA$554,MATCH($D$7,Tariff!$G$7:$G$554,0)+2,MATCH("Destination Port",Tariff!$B$7:$AA$7,0)),""),"")} -> Fremantle | C14: {=IF($D$7=IFERROR(INDEX(Tariff!$B$7:$AA$554,MATCH($D$7,Tariff!$G$7:$G$554,0)+2,MATCH("Origin Port",Tariff!$B$7:$AA$7,0)),""),IFERROR(INDEX(Tariff!$B$7:$AA$554,MATCH($D$7,Tariff!$G$7:$G$554,0)+2,MATCH(C11,Tariff!$B$7:$AA$7,0)),""),"")} -> USD | D14: {=IF($D$7=IFERROR(INDEX(Tariff!$B$7:$AA$554,MATCH($D$7,Tariff!$G$7:$G$554,0)+2,MATCH("Origin Port",Tariff!$B$7:$AA$7,0)),""),IFERROR(INDEX(Tariff!$B$7:$AA$554,MATCH($D$7,Tariff!$G$7:$G$554,0)+2,MATCH(D11,Tariff!$B$7:$AA$7,0)),""),"")} -> 40 | E14: {=IF($D$7=IFERROR(INDEX(Tariff!$B$7:$AA$554,MATCH($D$7,Tariff!$G$7:$G$554,0)+2,MATCH("Origin Port",Tariff!$B$7:$AA$7,0)),""),IFERROR(INDEX(Tariff!$B$7:$AA$554,MATCH($D$7,Tariff!$G$7:$G$554,0)+2,MATCH(E11,Tariff!$B$7:$AA$7,0)),""),"")} -> 40 | F14: {=IF($D$7=IFERROR(INDEX(Tariff!$B$7:$AA$554,MATCH($D$7,Tariff!$G$7:$G$554,0)+2,MATCH("Origin Port",Tariff!$B$7:$AA$7,0)),""),IFERROR(INDEX(Tariff!$B$7:$AA$554,MATCH($D$7,Tariff!$G$7:$G$554,0)+2,MATCH(F11,Tariff!$B$7:$AA$7,0)),""),"")} -> 40 | G14: {=IF($D$7=IFERROR(INDEX(Tariff!$B$7:$AA$554,MATCH($D$7,Tariff!$G$7:$G$554,0)+2,MATCH("Origin Port",Tariff!$B$7:$AA$7,0)),""),IFERROR(INDEX(Tariff!$B$7:$AA$554,MATCH($D$7,Tariff!$G$7:$G$554,0)+2,MATCH(G11,Tariff!$B$7:$AA$7,0)),""),"")} -> N/A | H14: {=IF($D$7=IFERROR(INDEX(Tariff!$B$7:$AA$554,MATCH($D$7,Tariff!$G$7:$G$554,0)+2,MATCH("Origin Port",Tariff!$B$7:$AA$7,0)),""),IFERROR(INDEX(Tariff!$B$7:$AA$554,MATCH($D$7,Tariff!$G$7:$G$554,0)+2,MATCH(H11,Tariff!$B$7:$AA$7,0)),""),"")} -> N/A | I14: {=IF($D$7=IFERROR(INDEX(Tariff!$B$7:$AA$554,MATCH($D$7,Tariff!$G$7:$G$554,0)+2,MATCH("Origin Port",Tariff!$B$7:$AA$7,0)),""),IFERROR(INDEX(Tariff!$B$7:$AA$554,MATCH($D$7,Tariff!$G$7:$G$554,0)+2,MATCH(I11,Tariff!$B$7:$AA$7,0)),""),"")} -> 3 | J14: {=IF($D$7=IFERROR(INDEX(Tariff!$B$7:$AA$554,MATCH($D$7,Tariff!$G$7:$G$554,0)+2,MATCH("Origin Port",Tariff!$B$7:$AA$7,0)),""),IFERROR(INDEX(Tariff!$B$7:$AA$554,MATCH($D$7,Tariff!$G$7:$G$554,0)+2,MATCH(J11,Tariff!$B$7:$AA$7,0)),""),"")} -> 10 | ... P14: {=IF($D$7=IFERROR(INDEX(Tariff!$B$7:$AA$554,MATCH($D$7,Tariff!$G$7:$G$554,0)+2,MATCH("Origin Port",Tariff!$B$7:$AA$7,0)),""),IFERROR(INDEX(Tariff!$B$7:$AA$554,MATCH($D$7,Tariff!$G$7:$G$554,0)+2,MATCH(P11,Tariff!$B$7:$AA$7,0)),""),"")} -> 46265
B15: {=IF($D$7=IFERROR(INDEX(Tariff!$B$7:$AA$554,MATCH($D$7,Tariff!$G$7:$G$554,0)+3,MATCH("Origin Port",Tariff!$B$7:$AA$7,0)),""),IFERROR(INDEX(Tariff!$B$7:$AA$554,MATCH($D$7,Tariff!$G$7:$G$554,0)+3,MATCH("Destination Port",Tariff!$B$7:$AA$7,0)),""),"")} -> Brisbane | C15: {=IF($D$7=IFERROR(INDEX(Tariff!$B$7:$AA$554,MATCH($D$7,Tariff!$G$7:$G$554,0)+3,MATCH("Origin Port",Tariff!$B$7:$AA$7,0)),""),IFERROR(INDEX(Tariff!$B$7:$AA$554,MATCH($D$7,Tariff!$G$7:$G$554,0)+3,MATCH(C11,Tariff!$B$7:$AA$7,0)),""),"")} -> USD | D15: {=IF($D$7=IFERROR(INDEX(Tariff!$B$7:$AA$554,MATCH($D$7,Tariff!$G$7:$G$554,0)+3,MATCH("Origin Port",Tariff!$B$7:$AA$7,0)),""),IFERROR(INDEX(Tariff!$B$7:$AA$554,MATCH($D$7,Tariff!$G$7:$G$554,0)+3,MATCH(D11,Tariff!$B$7:$AA$7,0)),""),"")} -> 33 | E15: {=IF($D$7=IFERROR(INDEX(Tariff!$B$7:$AA$554,MATCH($D$7,Tariff!$G$7:$G$554,0)+3,MATCH("Origin Port",Tariff!$B$7:$AA$7,0)),""),IFERROR(INDEX(Tariff!$B$7:$AA$554,MATCH($D$7,Tariff!$G$7:$G$554,0)+3,MATCH(E11,Tariff!$B$7:$AA$7,0)),""),"")} -> 33 | F15: {=IF($D$7=IFERROR(INDEX(Tariff!$B$7:$AA$554,MATCH($D$7,Tariff!$G$7:$G$554,0)+3,MATCH("Origin Port",Tariff!$B$7:$AA$7,0)),""),IFERROR(INDEX(Tariff!$B$7:$AA$554,MATCH($D$7,Tariff!$G$7:$G$554,0)+3,MATCH(F11,Tariff!$B$7:$AA$7,0)),""),"")} -> 33 | G15: {=IF($D$7=IFERROR(INDEX(Tariff!$B$7:$AA$554,MATCH($D$7,Tariff!$G$7:$G$554,0)+3,MATCH("Origin Port",Tariff!$B$7:$AA$7,0)),""),IFERROR(INDEX(Tariff!$B$7:$AA$554,MATCH($D$7,Tariff!$G$7:$G$554,0)+3,MATCH(G11,Tariff!$B$7:$AA$7,0)),""),"")} -> N/A | H15: {=IF($D$7=IFERROR(INDEX(Tariff!$B$7:$AA$554,MATCH($D$7,Tariff!$G$7:$G$554,0)+3,MATCH("Origin Port",Tariff!$B$7:$AA$7,0)),""),IFERROR(INDEX(Tariff!$B$7:$AA$554,MATCH($D$7,Tariff!$G$7:$G$554,0)+3,MATCH(H11,Tariff!$B$7:$AA$7,0)),""),"")} -> N/A | I15: {=IF($D$7=IFERROR(INDEX(Tariff!$B$7:$AA$554,MATCH($D$7,Tariff!$G$7:$G$554,0)+3,MATCH("Origin Port",Tariff!$B$7:$AA$7,0)),""),IFERROR(INDEX(Tariff!$B$7:$AA$554,MATCH($D$7,Tariff!$G$7:$G$554,0)+3,MATCH(I11,Tariff!$B$7:$AA$7,0)),""),"")} -> 3 | J15: {=IF($D$7=IFERROR(INDEX(Tariff!$B$7:$AA$554,MATCH($D$7,Tariff!$G$7:$G$554,0)+3,MATCH("Origin Port",Tariff!$B$7:$AA$7,0)),""),IFERROR(INDEX(Tariff!$B$7:$AA$554,MATCH($D$7,Tariff!$G$7:$G$554,0)+3,MATCH(J11,Tariff!$B$7:$AA$7,0)),""),"")} -> 10 | ... P15: {=IF($D$7=IFERROR(INDEX(Tariff!$B$7:$AA$554,MATCH($D$7,Tariff!$G$7:$G$554,0)+3,MATCH("Origin Port",Tariff!$B$7:$AA$7,0)),""),IFERROR(INDEX(Tariff!$B$7:$AA$554,MATCH($D$7,Tariff!$G$7:$G$554,0)+3,MATCH(P11,Tariff!$B$7:$AA$7,0)),""),"")} -> 46265
B16: {=IF($D$7=IFERROR(INDEX(Tariff!$B$7:$AA$554,MATCH($D$7,Tariff!$G$7:$G$554,0)+4,MATCH("Origin Port",Tariff!$B$7:$AA$7,0)),""),IFERROR(INDEX(Tariff!$B$7:$AA$554,MATCH($D$7,Tariff!$G$7:$G$554,0)+4,MATCH("Destination Port",Tariff!$B$7:$AA$7,0)),""),"")} -> Adelaide | C16: {=IF($D$7=IFERROR(INDEX(Tariff!$B$7:$AA$554,MATCH($D$7,Tariff!$G$7:$G$554,0)+4,MATCH("Origin Port",Tariff!$B$7:$AA$7,0)),""),IFERROR(INDEX(Tariff!$B$7:$AA$554,MATCH($D$7,Tariff!$G$7:$G$554,0)+4,MATCH(C11,Tariff!$B$7:$AA$7,0)),""),"")} -> USD | D16: {=IF($D$7=IFERROR(INDEX(Tariff!$B$7:$AA$554,MATCH($D$7,Tariff!$G$7:$G$554,0)+4,MATCH("Origin Port",Tariff!$B$7:$AA$7,0)),""),IFERROR(INDEX(Tariff!$B$7:$AA$554,MATCH($D$7,Tariff!$G$7:$G$554,0)+4,MATCH(D11,Tariff!$B$7:$AA$7,0)),""),"")} -> 73 | E16: {=IF($D$7=IFERROR(INDEX(Tariff!$B$7:$AA$554,MATCH($D$7,Tariff!$G$7:$G$554,0)+4,MATCH("Origin Port",Tariff!$B$7:$AA$7,0)),""),IFERROR(INDEX(Tariff!$B$7:$AA$554,MATCH($D$7,Tariff!$G$7:$G$554,0)+4,MATCH(E11,Tariff!$B$7:$AA$7,0)),""),"")} -> 73 | F16: {=IF($D$7=IFERROR(INDEX(Tariff!$B$7:$AA$554,MATCH($D$7,Tariff!$G$7:$G$554,0)+4,MATCH("Origin Port",Tariff!$B$7:$AA$7,0)),""),IFERROR(INDEX(Tariff!$B$7:$AA$554,MATCH($D$7,Tariff!$G$7:$G$554,0)+4,MATCH(F11,Tariff!$B$7:$AA$7,0)),""),"")} -> 73 | G16: {=IF($D$7=IFERROR(INDEX(Tariff!$B$7:$AA$554,MATCH($D$7,Tariff!$G$7:$G$554,0)+4,MATCH("Origin Port",Tariff!$B$7:$AA$7,0)),""),IFERROR(INDEX(Tariff!$B$7:$AA$554,MATCH($D$7,Tariff!$G$7:$G$554,0)+4,MATCH(G11,Tariff!$B$7:$AA$7,0)),""),"")} -> N/A | H16: {=IF($D$7=IFERROR(INDEX(Tariff!$B$7:$AA$554,MATCH($D$7,Tariff!$G$7:$G$554,0)+4,MATCH("Origin Port",Tariff!$B$7:$AA$7,0)),""),IFERROR(INDEX(Tariff!$B$7:$AA$554,MATCH($D$7,Tariff!$G$7:$G$554,0)+4,MATCH(H11,Tariff!$B$7:$AA$7,0)),""),"")} -> N/A | I16: {=IF($D$7=IFERROR(INDEX(Tariff!$B$7:$AA$554,MATCH($D$7,Tariff!$G$7:$G$554,0)+4,MATCH("Origin Port",Tariff!$B$7:$AA$7,0)),""),IFERROR(INDEX(Tariff!$B$7:$AA$554,MATCH($D$7,Tariff!$G$7:$G$554,0)+4,MATCH(I11,Tariff!$B$7:$AA$7,0)),""),"")} -> 3 | J16: {=IF($D$7=IFERROR(INDEX(Tariff!$B$7:$AA$554,MATCH($D$7,Tariff!$G$7:$G$554,0)+4,MATCH("Origin Port",Tariff!$B$7:$AA$7,0)),""),IFERROR(INDEX(Tariff!$B$7:$AA$554,MATCH($D$7,Tariff!$G$7:$G$554,0)+4,MATCH(J11,Tariff!$B$7:$AA$7,0)),""),"")} -> 10 | ... P16: {=IF($D$7=IFERROR(INDEX(Tariff!$B$7:$AA$554,MATCH($D$7,Tariff!$G$7:$G$554,0)+4,MATCH("Origin Port",Tariff!$B$7:$AA$7,0)),""),IFERROR(INDEX(Tariff!$B$7:$AA$554,MATCH($D$7,Tariff!$G$7:$G$554,0)+4,MATCH(P11,Tariff!$B$7:$AA$7,0)),""),"")} -> 46265
B17: {=IF($D$7=IFERROR(INDEX(Tariff!$B$7:$AA$554,MATCH($D$7,Tariff!$G$7:$G$554,0)+5,MATCH("Origin Port",Tariff!$B$7:$AA$7,0)),""),IFERROR(INDEX(Tariff!$B$7:$AA$554,MATCH($D$7,Tariff!$G$7:$G$554,0)+5,MATCH("Destination Port",Tariff!$B$7:$AA$7,0)),""),"")} | C17: {=IF($D$7=IFERROR(INDEX(Tariff!$B$7:$AA$554,MATCH($D$7,Tariff!$G$7:$G$554,0)+5,MATCH("Origin Port",Tariff!$B$7:$AA$7,0)),""),IFERROR(INDEX(Tariff!$B$7:$AA$554,MATCH($D$7,Tariff!$G$7:$G$554,0)+5,MATCH(C11,Tariff!$B$7:$AA$7,0)),""),"")} | D17: {=IF($D$7=IFERROR(INDEX(Tariff!$B$7:$AA$554,MATCH($D$7,Tariff!$G$7:$G$554,0)+5,MATCH("Origin Port",Tariff!$B$7:$AA$7,0)),""),IFERROR(INDEX(Tariff!$B$7:$AA$554,MATCH($D$7,Tariff!$G$7:$G$554,0)+5,MATCH(D11,Tariff!$B$7:$AA$7,0)),""),"")} | E17: {=IF($D$7=IFERROR(INDEX(Tariff!$B$7:$AA$554,MATCH($D$7,Tariff!$G$7:$G$554,0)+5,MATCH("Origin Port",Tariff!$B$7:$AA$7,0)),""),IFERROR(INDEX(Tariff!$B$7:$AA$554,MATCH($D$7,Tariff!$G$7:$G$554,0)+5,MATCH(E11,Tariff!$B$7:$AA$7,0)),""),"")} | F17: {=IF($D$7=IFERROR(INDEX(Tariff!$B$7:$AA$554,MATCH($D$7,Tariff!$G$7:$G$554,0)+5,MATCH("Origin Port",Tariff!$B$7:$AA$7,0)),""),IFERROR(INDEX(Tariff!$B$7:$AA$554,MATCH($D$7,Tariff!$G$7:$G$554,0)+5,MATCH(F11,Tariff!$B$7:$AA$7,0)),""),"")} | G17: {=IF($D$7=IFERROR(INDEX(Tariff!$B$7:$AA$554,MATCH($D$7,Tariff!$G$7:$G$554,0)+5,MATCH("Origin Port",Tariff!$B$7:$AA$7,0)),""),IFERROR(INDEX(Tariff!$B$7:$AA$554,MATCH($D$7,Tariff!$G$7:$G$554,0)+5,MATCH(G11,Tariff!$B$7:$AA$7,0)),""),"")} | H17: {=IF($D$7=IFERROR(INDEX(Tariff!$B$7:$AA$554,MATCH($D$7,Tariff!$G$7:$G$554,0)+5,MATCH("Origin Port",Tariff!$B$7:$AA$7,0)),""),IFERROR(INDEX(Tariff!$B$7:$AA$554,MATCH($D$7,Tariff!$G$7:$G$554,0)+5,MATCH(H11,Tariff!$B$7:$AA$7,0)),""),"")} | I17: {=IF($D$7=IFERROR(INDEX(Tariff!$B$7:$AA$554,MATCH($D$7,Tariff!$G$7:$G$554,0)+5,MATCH("Origin Port",Tariff!$B$7:$AA$7,0)),""),IFERROR(INDEX(Tariff!$B$7:$AA$554,MATCH($D$7,Tariff!$G$7:$G$554,0)+5,MATCH(I11,Tariff!$B$7:$AA$7,0)),""),"")} | J17: {=IF($D$7=IFERROR(INDEX(Tariff!$B$7:$AA$554,MATCH($D$7,Tariff!$G$7:$G$554,0)+5,MATCH("Origin Port",Tariff!$B$7:$AA$7,0)),""),IFERROR(INDEX(Tariff!$B$7:$AA$554,MATCH($D$7,Tariff!$G$7:$G$554,0)+5,MATCH(J11,Tariff!$B$7:$AA$7,0)),""),"")} | ... P17: {=IF($D$7=IFERROR(INDEX(Tariff!$B$7:$AA$554,MATCH($D$7,Tariff!$G$7:$G$554,0)+5,MATCH("Origin Port",Tariff!$B$7:$AA$7,0)),""),IFERROR(INDEX(Tariff!$B$7:$AA$554,MATCH($D$7,Tariff!$G$7:$G$554,0)+5,MATCH(P11,Tariff!$B$7:$AA$7,0)),""),"")}
B18: {=IF($D$7=IFERROR(INDEX(Tariff!$B$7:$AA$554,MATCH($D$7,Tariff!$G$7:$G$554,0)+6,MATCH("Origin Port",Tariff!$B$7:$AA$7,0)),""),IFERROR(INDEX(Tariff!$B$7:$AA$554,MATCH($D$7,Tariff!$G$7:$G$554,0)+6,MATCH("Destination Port",Tariff!$B$7:$AA$7,0)),""),"")} | C18: {=IF($D$7=IFERROR(INDEX(Tariff!$B$7:$AA$554,MATCH($D$7,Tariff!$G$7:$G$554,0)+6,MATCH("Origin Port",Tariff!$B$7:$AA$7,0)),""),IFERROR(INDEX(Tariff!$B$7:$AA$554,MATCH($D$7,Tariff!$G$7:$G$554,0)+6,MATCH(C11,Tariff!$B$7:$AA$7,0)),""),"")} | D18: {=IF($D$7=IFERROR(INDEX(Tariff!$B$7:$AA$554,MATCH($D$7,Tariff!$G$7:$G$554,0)+6,MATCH("Origin Port",Tariff!$B$7:$AA$7,0)),""),IFERROR(INDEX(Tariff!$B$7:$AA$554,MATCH($D$7,Tariff!$G$7:$G$554,0)+6,MATCH(D11,Tariff!$B$7:$AA$7,0)),""),"")} | E18: {=IF($D$7=IFERROR(INDEX(Tariff!$B$7:$AA$554,MATCH($D$7,Tariff!$G$7:$G$554,0)+6,MATCH("Origin Port",Tariff!$B$7:$AA$7,0)),""),IFERROR(INDEX(Tariff!$B$7:$AA$554,MATCH($D$7,Tariff!$G$7:$G$554,0)+6,MATCH(E11,Tariff!$B$7:$AA$7,0)),""),"")} | F18: {=IF($D$7=IFERROR(INDEX(Tariff!$B$7:$AA$554,MATCH($D$7,Tariff!$G$7:$G$554,0)+6,MATCH("Origin Port",Tariff!$B$7:$AA$7,0)),""),IFERROR(INDEX(Tariff!$B$7:$AA$554,MATCH($D$7,Tariff!$G$7:$G$554,0)+6,MATCH(F11,Tariff!$B$7:$AA$7,0)),""),"")} | G18: {=IF($D$7=IFERROR(INDEX(Tariff!$B$7:$AA$554,MATCH($D$7,Tariff!$G$7:$G$554,0)+6,MATCH("Origin Port",Tariff!$B$7:$AA$7,0)),""),IFERROR(INDEX(Tariff!$B$7:$AA$554,MATCH($D$7,Tariff!$G$7:$G$554,0)+6,MATCH(G11,Tariff!$B$7:$AA$7,0)),""),"")} | H18: {=IF($D$7=IFERROR(INDEX(Tariff!$B$7:$AA$554,MATCH($D$7,Tariff!$G$7:$G$554,0)+6,MATCH("Origin Port",Tariff!$B$7:$AA$7,0)),""),IFERROR(INDEX(Tariff!$B$7:$AA$554,MATCH($D$7,Tariff!$G$7:$G$554,0)+6,MATCH(H11,Tariff!$B$7:$AA$7,0)),""),"")} | I18: {=IF($D$7=IFERROR(INDEX(Tariff!$B$7:$AA$554,MATCH($D$7,Tariff!$G$7:$G$554,0)+6,MATCH("Origin Port",Tariff!$B$7:$AA$7,0)),""),IFERROR(INDEX(Tariff!$B$7:$AA$554,MATCH($D$7,Tariff!$G$7:$G$554,0)+6,MATCH(I11,Tariff!$B$7:$AA$7,0)),""),"")} | J18: {=IF($D$7=IFERROR(INDEX(Tariff!$B$7:$AA$554,MATCH($D$7,Tariff!$G$7:$G$554,0)+6,MATCH("Origin Port",Tariff!$B$7:$AA$7,0)),""),IFERROR(INDEX(Tariff!$B$7:$AA$554,MATCH($D$7,Tariff!$G$7:$G$554,0)+6,MATCH(J11,Tariff!$B$7:$AA$7,0)),""),"")} | ... P18: {=IF($D$7=IFERROR(INDEX(Tariff!$B$7:$AA$554,MATCH($D$7,Tariff!$G$7:$G$554,0)+6,MATCH("Origin Port",Tariff!$B$7:$AA$7,0)),""),IFERROR(INDEX(Tariff!$B$7:$AA$554,MATCH($D$7,Tariff!$G$7:$G$554,0)+6,MATCH(P11,Tariff!$B$7:$AA$7,0)),""),"")}
B19: {=IF($D$7=IFERROR(INDEX(Tariff!$B$7:$AA$510,MATCH($D$7,Tariff!$G$7:$G$510,0)+7,MATCH("Origin Port",Tariff!$B$7:$AA$7,0)),""),IFERROR(INDEX(Tariff!$B$7:$AA$510,MATCH($D$7,Tariff!$G$7:$G$510,0)+7,MATCH("Destination Port",Tariff!$B$7:$AA$7,0)),""),"")} | C19: {=IF($D$7=IFERROR(INDEX(Tariff!$B$7:$AA$510,MATCH($D$7,Tariff!$G$7:$G$510,0)+7,MATCH("Origin Port",Tariff!$B$7:$AA$7,0)),""),IFERROR(INDEX(Tariff!$B$7:$AA$510,MATCH($D$7,Tariff!$G$7:$G$510,0)+7,MATCH(C11,Tariff!$B$7:$AA$7,0)),""),"")} | D19: {=IF($D$7=IFERROR(INDEX(Tariff!$B$7:$AA$510,MATCH($D$7,Tariff!$G$7:$G$510,0)+7,MATCH("Origin Port",Tariff!$B$7:$AA$7,0)),""),IFERROR(INDEX(Tariff!$B$7:$AA$510,MATCH($D$7,Tariff!$G$7:$G$510,0)+7,MATCH(D11,Tariff!$B$7:$AA$7,0)),""),"")} | E19: {=IF($D$7=IFERROR(INDEX(Tariff!$B$7:$AA$510,MATCH($D$7,Tariff!$G$7:$G$510,0)+7,MATCH("Origin Port",Tariff!$B$7:$AA$7,0)),""),IFERROR(INDEX(Tariff!$B$7:$AA$510,MATCH($D$7,Tariff!$G$7:$G$510,0)+7,MATCH(E11,Tariff!$B$7:$AA$7,0)),""),"")} | F19: {=IF($D$7=IFERROR(INDEX(Tariff!$B$7:$AA$510,MATCH($D$7,Tariff!$G$7:$G$510,0)+7,MATCH("Origin Port",Tariff!$B$7:$AA$7,0)),""),IFERROR(INDEX(Tariff!$B$7:$AA$510,MATCH($D$7,Tariff!$G$7:$G$510,0)+7,MATCH(F11,Tariff!$B$7:$AA$7,0)),""),"")} | G19: {=IF($D$7=IFERROR(INDEX(Tariff!$B$7:$AA$510,MATCH($D$7,Tariff!$G$7:$G$510,0)+7,MATCH("Origin Port",Tariff!$B$7:$AA$7,0)),""),IFERROR(INDEX(Tariff!$B$7:$AA$510,MATCH($D$7,Tariff!$G$7:$G$510,0)+7,MATCH(G11,Tariff!$B$7:$AA$7,0)),""),"")} | H19: {=IF($D$7=IFERROR(INDEX(Tariff!$B$7:$AA$510,MATCH($D$7,Tariff!$G$7:$G$510,0)+7,MATCH("Origin Port",Tariff!$B$7:$AA$7,0)),""),IFERROR(INDEX(Tariff!$B$7:$AA$510,MATCH($D$7,Tariff!$G$7:$G$510,0)+7,MATCH(H11,Tariff!$B$7:$AA$7,0)),""),"")} | I19: {=IF($D$7=IFERROR(INDEX(Tariff!$B$7:$AA$510,MATCH($D$7,Tariff!$G$7:$G$510,0)+7,MATCH("Origin Port",Tariff!$B$7:$AA$7,0)),""),IFERROR(INDEX(Tariff!$B$7:$AA$510,MATCH($D$7,Tariff!$G$7:$G$510,0)+7,MATCH(I11,Tariff!$B$7:$AA$7,0)),""),"")} | J19: {=IF($D$7=IFERROR(INDEX(Tariff!$B$7:$AA$510,MATCH($D$7,Tariff!$G$7:$G$510,0)+7,MATCH("Origin Port",Tariff!$B$7:$AA$7,0)),""),IFERROR(INDEX(Tariff!$B$7:$AA$510,MATCH($D$7,Tariff!$G$7:$G$510,0)+7,MATCH(J11,Tariff!$B$7:$AA$7,0)),""),"")} | ... P19: {=IF($D$7=IFERROR(INDEX(Tariff!$B$7:$AA$510,MATCH($D$7,Tariff!$G$7:$G$510,0)+7,MATCH("Origin Port",Tariff!$B$7:$AA$7,0)),""),IFERROR(INDEX(Tariff!$B$7:$AA$510,MATCH($D$7,Tariff!$G$7:$G$510,0)+7,MATCH(P11,Tariff!$B$7:$AA$7,0)),""),"")}
B20: {=IF($D$7=IFERROR(INDEX(Tariff!$B$7:$AA$510,MATCH($D$7,Tariff!$G$7:$G$510,0)+8,MATCH("Origin Port",Tariff!$B$7:$AA$7,0)),""),IFERROR(INDEX(Tariff!$B$7:$AA$510,MATCH($D$7,Tariff!$G$7:$G$510,0)+8,MATCH("Destination Port",Tariff!$B$7:$AA$7,0)),""),"")} | C20: {=IF($D$7=IFERROR(INDEX(Tariff!$B$7:$AA$510,MATCH($D$7,Tariff!$G$7:$G$510,0)+8,MATCH("Origin Port",Tariff!$B$7:$AA$7,0)),""),IFERROR(INDEX(Tariff!$B$7:$AA$510,MATCH($D$7,Tariff!$G$7:$G$510,0)+8,MATCH(C11,Tariff!$B$7:$AA$7,0)),""),"")} | D20: {=IF($D$7=IFERROR(INDEX(Tariff!$B$7:$AA$510,MATCH($D$7,Tariff!$G$7:$G$510,0)+8,MATCH("Origin Port",Tariff!$B$7:$AA$7,0)),""),IFERROR(INDEX(Tariff!$B$7:$AA$510,MATCH($D$7,Tariff!$G$7:$G$510,0)+8,MATCH(D11,Tariff!$B$7:$AA$7,0)),""),"")} | E20: {=IF($D$7=IFERROR(INDEX(Tariff!$B$7:$AA$510,MATCH($D$7,Tariff!$G$7:$G$510,0)+8,MATCH("Origin Port",Tariff!$B$7:$AA$7,0)),""),IFERROR(INDEX(Tariff!$B$7:$AA$510,MATCH($D$7,Tariff!$G$7:$G$510,0)+8,MATCH(E11,Tariff!$B$7:$AA$7,0)),""),"")} | F20: {=IF($D$7=IFERROR(INDEX(Tariff!$B$7:$AA$510,MATCH($D$7,Tariff!$G$7:$G$510,0)+8,MATCH("Origin Port",Tariff!$B$7:$AA$7,0)),""),IFERROR(INDEX(Tariff!$B$7:$AA$510,MATCH($D$7,Tariff!$G$7:$G$510,0)+8,MATCH(F11,Tariff!$B$7:$AA$7,0)),""),"")} | G20: {=IF($D$7=IFERROR(INDEX(Tariff!$B$7:$AA$510,MATCH($D$7,Tariff!$G$7:$G$510,0)+8,MATCH("Origin Port",Tariff!$B$7:$AA$7,0)),""),IFERROR(INDEX(Tariff!$B$7:$AA$510,MATCH($D$7,Tariff!$G$7:$G$510,0)+8,MATCH(G11,Tariff!$B$7:$AA$7,0)),""),"")} | H20: {=IF($D$7=IFERROR(INDEX(Tariff!$B$7:$AA$510,MATCH($D$7,Tariff!$G$7:$G$510,0)+8,MATCH("Origin Port",Tariff!$B$7:$AA$7,0)),""),IFERROR(INDEX(Tariff!$B$7:$AA$510,MATCH($D$7,Tariff!$G$7:$G$510,0)+8,MATCH(H11,Tariff!$B$7:$AA$7,0)),""),"")} | I20: {=IF($D$7=IFERROR(INDEX(Tariff!$B$7:$AA$510,MATCH($D$7,Tariff!$G$7:$G$510,0)+8,MATCH("Origin Port",Tariff!$B$7:$AA$7,0)),""),IFERROR(INDEX(Tariff!$B$7:$AA$510,MATCH($D$7,Tariff!$G$7:$G$510,0)+8,MATCH(I11,Tariff!$B$7:$AA$7,0)),""),"")} | J20: {=IF($D$7=IFERROR(INDEX(Tariff!$B$7:$AA$510,MATCH($D$7,Tariff!$G$7:$G$510,0)+8,MATCH("Origin Port",Tariff!$B$7:$AA$7,0)),""),IFERROR(INDEX(Tariff!$B$7:$AA$510,MATCH($D$7,Tariff!$G$7:$G$510,0)+8,MATCH(J11,Tariff!$B$7:$AA$7,0)),""),"")} | ... P20: {=IF($D$7=IFERROR(INDEX(Tariff!$B$7:$AA$510,MATCH($D$7,Tariff!$G$7:$G$510,0)+8,MATCH("Origin Port",Tariff!$B$7:$AA$7,0)),""),IFERROR(INDEX(Tariff!$B$7:$AA$510,MATCH($D$7,Tariff!$G$7:$G$510,0)+8,MATCH(P11,Tariff!$B$7:$AA$7,0)),""),"")}
B21: {=IF($D$7=IFERROR(INDEX(Tariff!$B$7:$AA$510,MATCH($D$7,Tariff!$G$7:$G$510,0)+9,MATCH("Origin Port",Tariff!$B$7:$AA$7,0)),""),IFERROR(INDEX(Tariff!$B$7:$AA$510,MATCH($D$7,Tariff!$G$7:$G$510,0)+9,MATCH("Destination Port",Tariff!$B$7:$AA$7,0)),""),"")} | C21: {=IF($D$7=IFERROR(INDEX(Tariff!$B$7:$AA$510,MATCH($D$7,Tariff!$G$7:$G$510,0)+9,MATCH("Origin Port",Tariff!$B$7:$AA$7,0)),""),IFERROR(INDEX(Tariff!$B$7:$AA$510,MATCH($D$7,Tariff!$G$7:$G$510,0)+9,MATCH(C11,Tariff!$B$7:$AA$7,0)),""),"")} | D21: {=IF($D$7=IFERROR(INDEX(Tariff!$B$7:$AA$510,MATCH($D$7,Tariff!$G$7:$G$510,0)+9,MATCH("Origin Port",Tariff!$B$7:$AA$7,0)),""),IFERROR(INDEX(Tariff!$B$7:$AA$510,MATCH($D$7,Tariff!$G$7:$G$510,0)+9,MATCH(D11,Tariff!$B$7:$AA$7,0)),""),"")} | E21: {=IF($D$7=IFERROR(INDEX(Tariff!$B$7:$AA$510,MATCH($D$7,Tariff!$G$7:$G$510,0)+9,MATCH("Origin Port",Tariff!$B$7:$AA$7,0)),""),IFERROR(INDEX(Tariff!$B$7:$AA$510,MATCH($D$7,Tariff!$G$7:$G$510,0)+9,MATCH(E11,Tariff!$B$7:$AA$7,0)),""),"")} | F21: {=IF($D$7=IFERROR(INDEX(Tariff!$B$7:$AA$510,MATCH($D$7,Tariff!$G$7:$G$510,0)+9,MATCH("Origin Port",Tariff!$B$7:$AA$7,0)),""),IFERROR(INDEX(Tariff!$B$7:$AA$510,MATCH($D$7,Tariff!$G$7:$G$510,0)+9,MATCH(F11,Tariff!$B$7:$AA$7,0)),""),"")} | G21: {=IF($D$7=IFERROR(INDEX(Tariff!$B$7:$AA$510,MATCH($D$7,Tariff!$G$7:$G$510,0)+9,MATCH("Origin Port",Tariff!$B$7:$AA$7,0)),""),IFERROR(INDEX(Tariff!$B$7:$AA$510,MATCH($D$7,Tariff!$G$7:$G$510,0)+9,MATCH(G11,Tariff!$B$7:$AA$7,0)),""),"")} | H21: {=IF($D$7=IFERROR(INDEX(Tariff!$B$7:$AA$510,MATCH($D$7,Tariff!$G$7:$G$510,0)+9,MATCH("Origin Port",Tariff!$B$7:$AA$7,0)),""),IFERROR(INDEX(Tariff!$B$7:$AA$510,MATCH($D$7,Tariff!$G$7:$G$510,0)+9,MATCH(H11,Tariff!$B$7:$AA$7,0)),""),"")} | I21: {=IF($D$7=IFERROR(INDEX(Tariff!$B$7:$AA$510,MATCH($D$7,Tariff!$G$7:$G$510,0)+9,MATCH("Origin Port",Tariff!$B$7:$AA$7,0)),""),IFERROR(INDEX(Tariff!$B$7:$AA$510,MATCH($D$7,Tariff!$G$7:$G$510,0)+9,MATCH(I11,Tariff!$B$7:$AA$7,0)),""),"")} | J21: {=IF($D$7=IFERROR(INDEX(Tariff!$B$7:$AA$510,MATCH($D$7,Tariff!$G$7:$G$510,0)+9,MATCH("Origin Port",Tariff!$B$7:$AA$7,0)),""),IFERROR(INDEX(Tariff!$B$7:$AA$510,MATCH($D$7,Tariff!$G$7:$G$510,0)+9,MATCH(J11,Tariff!$B$7:$AA$7,0)),""),"")} | ... P21: {=IF($D$7=IFERROR(INDEX(Tariff!$B$7:$AA$510,MATCH($D$7,Tariff!$G$7:$G$510,0)+9,MATCH("Origin Port",Tariff!$B$7:$AA$7,0)),""),IFERROR(INDEX(Tariff!$B$7:$AA$510,MATCH($D$7,Tariff!$G$7:$G$510,0)+9,MATCH(P11,Tariff!$B$7:$AA$7,0)),""),"")}
C24: Note: Please refer to the Conditions tab
C25: {=IFERROR(INDEX(Tariff!$B$7:$AA$554,MATCH($D$7,Tariff!$G$7:$G$554,0)+0,MATCH("Conditions",Tariff!$B$7:$AA$7,0)),"")} -> Subject to applicable GRI, PSS, EFS
B26: vanguardlogistics.com

Sheet Cartage
B1: LCL Cartage | F1: Vanguard Logistics LCL Import Tariff
B4: Australia Cartage Rates
B7: Cartage Rates
B8: Description | C8: Sydney | D8: Melbourne | E8: Brisbane | F8: Adelaide | G8: Fremantle
B9: Metro Delivery, per w/m | C9: 28 | D9: 30 | E9: 28 | F9: 26 | G9: 30
B10: Minimum Charge | C10: 115 | D10: 120 | E10: 115 | F10: 115 | G10: 110
B11: Fuel Surcharge | C11: 0.33 | D11: 0.365 | E11: 0.32 | F11: 0.495 | G11: 0.4162
B12: Toll Surcharge | C12: 0.08 | D12: 0.064 | E12: 0.08 | F12: 0 | G12: 0
B13: Booking Fee | C13: 45 | D13: 45 | E13: 45 | F13: 45 | G13: 45
B14: Hazardous Surcharge | C14: $75.00 max 3 cbm | D14: 70 | E14: $125.00 max 3 cbm | F14: 60 | G14: on app.
B15: Conditions:
B16: * All rates in AUD
B17: * Fuel and Toll surcharges are calculated on the total cartage amount
B18: * Rates are valid for normal trailer and kerbside delivery only
B19: * Hazardous Surcharge is subject to approval
B20: * The above rates are not valid for personal effects
B21: * Demurrage charges may apply
B22: * Fuel Surcharge is subject to change without notice
B23: * Subject to GST
B24: ***IMPORTANT NOTE: Any cargo that is over 3 metres long is quoted on a case by case basis.

Sheet Prepaid Local Charges
B1: Local Charges | K1: Vanguard Logistics Import LCL Tariff
B2: Vanguard Wholesale Australian LCL Destination Charges
I4: Destination
B5: Origin | C5: Charge | D5: Charge Code | E5: Charge per | F5: Currency | G5: Sydney | H5: Melbourne | I5: Fremantle | J5: Brisbane | K5: Adelaide
B6: China | C6: Port Service Charge | D6: PSC | E6: w/m | F6: AUD | G6: 127 | H6: 130 | I6: 130 | J6: 127 | K6: 129
C7: Delivery Order | D7: DO | E7: BL | F7: AUD | G7: 65 | H7: 65 | I7: 65 | J7: 65 | K7: 65
B9: Asia ( Exluding China) | C9: Port Service Charge | D9: PSC | E9: w/m | F9: AUD | G9: 117 | H9: 120 | I9: 120 | J9: 117 | K9: 119
C10: Delivery Order | D10: DO | E10: BL | F10: AUD | G10: 65 | H10: 65 | I10: 65 | J10: 65 | K10: 65
B12: New Zealand | C12: Port Service Charge | D12: PSC | E12: w/m | F12: AUD | G12: 72 | H12: 75 | I12: 75 | J12: 72 | K12: 74
C13: Delivery Order | D13: DO | E13: BL | F13: AUD | G13: 65 | H13: 65 | I13: 65 | J13: 65 | K13: 65
B15: USA | C15: Port Service Charge | D15: PSC | E15: w/m | F15: AUD | G15: 75 | H15: 78 | I15: 78 | J15: 75 | K15: 77
C16: Delivery Order | D16: DO | E16: BL | F16: AUD | G16: 64 | H16: 64 | I16: 64 | J16: 64 | K16: 64
B18: United Kingdom | C18: Port Service Charge | D18: PSC | E18: w/m | F18: AUD | G18: 82 | H18: 85 | I18: 95 | J18: 92 | K18: 94
C19: Delivery Order | D19: DO | E19: BL | F19: AUD | G19: 45 | H19: 45 | I19: 45 | J19: 45 | K19: 45
B20: Europe Direct | C20: Port Service Charge | D20: PSC | E20: w/m | F20: AUD | G20: 102 | H20: 105
C21: Delivery Order | D21: DO | E21: BL | F21: AUD | G21: 65 | H21: 65
B23: Europe Via Asia | C23: Port Service Charge | D23: PSC | E23: w/m | F23: AUD | G23: 112 | H23: 115 | I23: 115 | J23: 112 | K23: 114
C24: Delivery Order | D24: DO | E24: BL | F24: AUD | G24: 65 | H24: 65 | I24: 65 | J24: 65 | K24: 65
B26: Rest of World Direct | C26: Port Service Charge | D26: PSC | E26: w/m | F26: AUD | G26: 107 | H26: 110 | I26: 110 | J26: 107 | K26: 109
C27: Delivery Order | D27: DO | E27: BL | F27: AUD | G27: 65 | H27: 65 | I27: 65 | J27: 65 | K27: 65
B29: Rest of World via Asia | C29: Port Service Charge | D29: PSC | E29: w/m | F29: AUD | G29: 117 | H29: 120 | I29: 20 | J29: 117 | K29: 119
C30: Delivery Order | D30: DO | E30: BL | F30: AUD | G30: 65 | H30: 65 | I30: 65 | J30: 65 | K30: 65
B32: All | C32: BMSB Processing Fee* | D32: BMSB | E32: BL | F32: AUD | G32: 35
B33: * The BMSB fee will apply to all cargo arriving in an FAK from a BMSB country, please refer to conditions tab for BMSB countries.

Sheet Collect Local Charges
B1: Local Charges | K1: Vanguard Logistics Import LCL Tariff
B2: Vanguard Wholesale Australian LCL Destination Charges
I4: Destination
B5: Origin | C5: Charge | D5: Charge Code | E5: Charge per | F5: Currency | G5: Sydney | H5: Melbourne | I5: Fremantle | J5: Brisbane | K5: Adelaide
B6: China / Hong Kong | C6: Port Service Charge | D6: PSC | E6: w/m | F6: AUD | G6: 82 | H6: 82 | I6: 82 | J6: 82 | K6: 84
C7: Delivery Order | D7: DO | E7: BL | F7: AUD | G7: 55 | H7: 55 | I7: 55 | J7: 55 | K7: 55
B9: Asia ( Exluding China) | C9: Port Service Charge | D9: PSC | E9: w/m | F9: AUD | G9: 95 | H9: 98 | I9: 98 | J9: 95 | K9: 97
C10: Delivery Order | D10: DO | E10: BL | F10: AUD | G10: 65 | H10: 65 | I10: 65 | J10: 65 | K10: 65
B12: New Zealand | C12: Port Service Charge | D12: PSC | E12: w/m | F12: AUD | G12: 75 | H12: 78 | I12: 78 | J12: 75 | K12: 77
C13: Delivery Order | D13: DO | E13: BL | F13: AUD | G13: 65 | H13: 65 | I13: 65 | J13: 65 | K13: 65
B15: USA | C15: Port Service Charge | D15: PSC | E15: w/m | F15: AUD | G15: 75 | H15: 78 | I15: 75 | J15: 75 | K15: 77
C16: Delivery Order | D16: DO | E16: BL | F16: AUD | G16: 64 | H16: 64 | I16: 64 | J16: 64 | K16: 64
B18: United Kingdom | C18: Port Service Charge | D18: PSC | E18: w/m | F18: AUD | G18: 85 | H18: 88 | I18: 98 | J18: 95 | K18: 97
C19: Delivery Order | D19: DO | E19: BL | F19: AUD | G19: 45 | H19: 45 | I19: 45 | J19: 45 | K19: 45
B20: Europe Direct | C20: Port Service Charge | D20: PSC | E20: w/m | F20: AUD | G20: 87 | H20: 89
C21: Delivery Order | D21: DO | E21: BL | F21: AUD | G21: 65 | H21: 65
B23: Europe Via Asia | C23: Port Service Charge | D23: PSC | E23: w/m | F23: AUD | G23: 97 | H23: 99 | I23: 100 | J23: 97 | K23: 99
C24: Delivery Order | D24: DO | E24: BL | F24: AUD | G24: 65 | H24: 65 | I24: 65 | J24: 65 | K24: 65
B26: Rest of World Direct | C26: Port Service Charge | D26: PSC | E26: w/m | F26: AUD | G26: 100 | H26: 103 | I26: 103 | J26: 100 | K26: 102
C27: Delivery Order | D27: DO | E27: BL | F27: AUD | G27: 65 | H27: 65 | I27: 65 | J27: 65 | K27: 65
B29: Rest of World via Asia | C29: Port Service Charge | D29: PSC | E29: w/m | F29: AUD | G29: 110 | H29: 113 | I29: 113 | J29: 110 | K29: 112
C30: Delivery Order | D30: DO | E30: BL | F30: AUD | G30: 65 | H30: 65 | I30: 65 | J30: 65 | K30: 65
B32: All | C32: BMSB Processing Fee* | D32: BMSB | E32: BL | F32: AUD | G32: 35
B33: * The BMSB fee will apply to all cargo arriving in an FAK from a BMSB country, please refer to conditions tab for BMSB countries.

Sheet Agent Search
B1: Vanguard Agents | F1: Vanguard Logistics Import LCL Tariff
B4: Search for a Vanguard agent
B7: Enter Origin Port Here ® | C7: Aarhus | G7: =IF(C7="","",(INDEX($B$29:$I$148,MATCH($C$7,$B$29:$B$148,),MATCH("Country",$B$29:$H$29,)))) -> Denmark
B10: Company | C10: =INDEX($B$29:$I$148, MATCH($C$7,$B$29:$B$148,), MATCH("Company",$B$29:$H$29,)) -> Greencarrier
B11: Address | C11: =INDEX($B$29:$I$148, MATCH($C$7,$B$29:$B$148,), MATCH("Address",$B$29:$H$29,)) -> Nyhavn 16, 2nd Floor DK-1051 Copenhagen K, Denmark
B12: Contact | C12: =INDEX($B$29:$I$148, MATCH($C$7,$B$29:$B$148,), MATCH("Contact",$B$29:$H$29,)) -> Janni Hartmann
B13: Phone | C13: =INDEX($B$29:$I$148, MATCH($C$7,$B$29:$B$148,), MATCH("Phone",$B$29:$H$29,)) -> +45 77330600
B14: Email | C14: =INDEX($B$29:$I$148, MATCH($C$7,$B$29:$B$148,), MATCH("email",$B$29:$H$29,)) -> export.gcc.se@greencarrier.com ; Janni.Hartmann@greencarrier.com
B29: Port | C29: Country | D29: Company | E29: Address | F29: Contact | G29: Phone | H29: email
B31: Chittagong | C31: Bangladesh | D31: Vanguard Logistics Services | E31: Monjur Building (1st Floor), 67 Agrabad C/A Agrabad, Chattogram-4100, Bangladesh | F31: Mizanur Rahman Kanchan Shill | G31: +880 9638 88 55 77 | H31: mizanur.rahman@vanguardlogistics.com kanchan.shill@vanguardlogistics.com
B32: Antwerp | C32: Belgium | D32: Vanguard Logistics Services | E32: Romeynsweel 8, 2030, Antwerpen | F32: Eva Bervoets | G32: +32 3 543 1800 | H32: eva.bervoets​@vanguardlogistics.com
B33: Santos | C33: Brazil | D33: Vanguard Logistics Services | E33: Av. Ana Costa, 433 – Cj 93 and 94 Gonzaga CEP 11060-003 Santos - SP, Brazil | F33: Maria Pilar | G33: +55 13 3229 7000 | H33: maria.pilar​@vanguardlogistics.com
B34: Phnom Penh | C34: Cambodia | D34: Vanguard Logistics Services (Cambodia) Pte Ltd | E34: No 4, Street 242, Sangkat Beungprolit, Khan 7 Makara, Phnom Penh, Cambodia | F34: Mr Ly Uy Ly | G34: 855-11 828388 | H34: ly.uyly@vls-cambodia.com
B35: Sihanoukville | C35: Cambodia | D35: Vanguard Logistics Services (Cambodia) Pte Ltd | E35: No 4, Street 242, Sangkat Beungprolit, Khan 7 Makara, Phnom Penh, Cambodia | F35: Mr Ly Uy Ly | G35: 855-11 828388 | H35: ly.uyly@vls-cambodia.com
B36: Montreal | C36: Canada | D36: Vanguard Logistics Services | E36: 465 Rue St-Jean, #700 Montreal,QC Canada H2Y 2R6 | F36: Operations | G36: +1 438 260 1832 | H36: exports.ca@vanguardlogistics.com antoinette.de.rosa@vanguardlogistics.com
B37: Toronto | C37: Canada | D37: Vanguard Logistics Services | E37: 1450 Meyerside Drive, Suite 402 Mississauga, Ontario Canada L5T 2 N5 Toronto | F37: Operations / Ashima Mehta | G37: +1 905 234 1650 | H37: exports.ca@vanguardlogistics.com ashima.mehta@vanguardlogistics.com
B38: Vancouver | C38: Canada | D38: Vanguard Logistics Services | E38: 1450 Meyerside Drive, Suite 402 Mississauga, Ontario Canada L5T 2 N5 Toronto | F38: Ashima Mehta | G38: +1 905-234-1650 | H38: exports.ca@vanguardlogistics.com ashima.mehta​@vanguardlogistics.com
B39: Dalian | C39: China | D39: Vanguard Logistics Services | E39: 20 Yide Street, Zhongshan District, Dalian 116001, China | F39: Mavis Li | G39: +86 411 3986 7765 | H39: mavis.li@vanguardlogistics.com
B40: Foshan | C40: China | D40: Vanguard Logistics Services | E40: Room 2003-2008, Guidu Building, No. 3007 Chunfeng Rd., Shenzhen, 518002 China | F40: Aly Zhong | G40: 8675582316764 | H40: aly.zhong​@vanguardlogistics.com
B41: Fuzhou | C41: China | D41: Vanguard Logistics Services | E41: Room 1621-1622, 3rd Building, Dong Er Huan Thaihot Plaza 11 Hengyu Road, Jin’an District, Fuzhou, Fujian, China 350011 | F41: Jessie Huang | G41: 86-591-8781 0020 | H41: jessie.huang@vanguardlogistics.com
B42: Guangzhou | C42: China | D42: Vanguard Logistics Services (Zhuhai) Ltd. - Guangzhou Branch | E42: Room 2201-7 Baihui Plaza, No. 193 Zhongshan 5 Road, Yuexiu District, Guangzhou, P.R.China 510030 | F42: Apple Dong | G42: 86-20-8364 9686 | H42: apple.dong@vanguardlogistics.com
B43: Huangpu | C43: China | D43: Vanguard Logistics Services (Zhuhai) Ltd. - Guangzhou Branch | E43: Room 2201-7 Baihui Plaza, No. 193 Zhongshan 5 Road, Yuexiu District, Guangzhou, P.R.China 510030 | F43: Apple Dong | G43: 86-20-8364 9686 | H43: apple.dong@vanguardlogistics.com
B44: Jiangmen | C44: China | D44: Vanguard Logisitic Services (HK) Ltd | E44: 36/ F Vicwood Plaza, 199 Des Voeux Road Central, Hong Kong | F44: Helen Cheng | G44: 852 3477 0123 | H44: helen.cheng@vanguardlogistics.com
B45: Ningbo | C45: China | D45: Vanguard Logistics Services | E45: 16/F Huanhe Center Block 1 No 168 Anbo Road Jiangdong District, Ningbo | F45: Eileen Tang | G45: +86 574 2766 6088 | H45: eileen.tang@vanguardlogistics.com
B46: Qingdao | C46: China | D46: Vanguard Logistics Services | E46: Unit A, F-H, 25/F, China-R international Mansion 2 Shandong Road Qingdao, China 266071 | F46: Roicy Li | G46: 86-532-8667 6812 | H46: roicy.li​@vanguardlogistics.com
B47: Shanghai | C47: China | D47: Vanguard Logistics Services | E47: 36/F BM Tower 218 Wusong Road Shanghai, China 200080 | F47: Ms Yoyo Zhang | G47: +86 21 2603 6117 | H47: yoyo.zhang@vanguardlogistics.com
B48: Shekou | C48: China | D48: Vanguard Logistics Services | E48: Room 2003-2008, Guidu Building, No. 3007 Chunfeng Rd., Shenzhen, 518002 China | F48: Daisy Zhong | G48: +86 755 8231 6839 | H48: daisy.zhong​@vanguardlogistics.com
B49: Shenzhen | C49: China | D49: Vanguard Logistics Services | E49: Room 2003-2008, Guidu Building, No. 3007 Chunfeng Rd., Shenzhen, 518002 China | F49: Daisy Zhong | G49: +86 755 8231 6839 | H49: daisy.zhong​@vanguardlogistics.com
B50: Shunde | C50: China | D50: Vanguard Logistics Services | E50: Room 2003-2008, Guidu Building, No. 3007 Chunfeng Rd., Shenzhen, 518002 China | F50: Aly Zhong | G50: 8675582316764 | H50: aly.zhong​@vanguardlogistics.com
B51: Tianjin | C51: China | D51: Vanguard Logistics Services | E51: Room 20H 20th Floor Teda Building 256 Jie Fang South Road Tianjin 300042, China | F51: Jenny Sun | G51: +86 22 5995 9312 | H51: jenny.sun@vanguardlogistics.com
B52: Xiamen | C52: China | D52: Vanguard Logistics Services | E52: Room 3001 The Bank Centre No. 189 Xia He Road Xiamen, Fujian, China 361003 | F52: Maggie Tang | G52: 86-592-2688 678 | H52: maggie.tang@vanguardlogistics.com
B53: Xingang | C53: China | D53: Vanguard Logistics Services | E53: Room 20H 20th Floor Teda Building 256 Jie Fang South Road Tianjin 300042, China | F53: Jenny Sun | G53: +86 22 5995 9312 | H53: jenny.sun@vanguardlogistics.com
B54: Yantian | C54: China | D54: Vanguard Logistics Services | E54: Room 2003-2008, Guidu Building, No. 3007 Chunfeng Rd., Shenzhen, 518002 China | F54: Daisy Zhong | G54: +86 755 8231 6839 | H54: daisy.zhong@vanguardlogistics.com
B55: Zhongshan | C55: China | D55: Vanguard Logistics Services | E55: Room 1511, Lihe International Financial Center, 16 Zhongshan 3rd Road, Zhongshan, Guangdong, China 528403 | F55: Kay Ng | G55: 86-760-8866 8707 | H55: kay.ng@vanguardlogistics.com
B56: Zhuhai | C56: China | D56: Vanguard Logisitic Services (HK) Ltd | E56: Units 1-2 and 4, 5th Floor, Production and Processing Center #3 1 Software Park Road, Zhuhai City, Guangdong, China 519080 | F56: Helen Cheng | G56: 852 3477 0123 | H56: helen.cheng@vanguardlogistics.com
B57: Aarhus | C57: Denmark | D57: Greencarrier | E57: Nyhavn 16, 2nd Floor DK-1051 Copenhagen K, Denmark | F57: Janni Hartmann | G57: +45 77330600 | H57: export.gcc.se@greencarrier.com ; Janni.Hartmann@greencarrier.com
B58: Copenhagen | C58: Denmark | D58: Greencarrier | E58: Nyhavn 16, 2nd Floor DK-1051 Copenhagen K, Denmark | F58: Janni Hartmann | G58: +45 77330600 | H58: export.gcc.se@greencarrier.com ; Janni.Hartmann@greencarrier.com
B59: Lautoka | C59: Fiji | D59: Vanguard Logistics Services (Fiji) | E59: 8 Rose Place Vunato Industrial Sub Division Lautoka | F59: Rizuana Begam | G59: (679) 666 0565 | H59: rizuana.begam@vanguardlogistics.com
B60: Suva | C60: Fiji | D60: Vanguard Logistics Services (Fiji) | E60: Lot 1 Foster Road Walubay Suva, Fiji | F60: Sangeeta Singh | G60: (679) 3315286 | H60: sangeeta.singh@vanguardlogistics.com
B61: Helsinki | C61: Finland | D61: Greencarrier | E61: Läkkisepäntie 23 FI-00620 Helsinki, Finland | F61: Nicolas Myrén | G61: +358 400 272 655 | H61: export.gcc.fi@greencarrier.com ; Nicolas.Myren@greencarrier.com
B62: Le Havre | C62: France | D62: Vanguard Logistics Services | E62: Romeynsweel 8, 2030, Antwerpen | F62: Eva Bervoets | G62: +32 3 543 1800 | H62: eva.bervoets​@vanguardlogistics.com
... B70: Chennai | C70: India | D70: Vanguard Logistics Services | E70: Olympia Cyberspace, 5th Floor, Arulaiyammanpet 2nd Street, Guindy, Chennai - 600032 Tamil Nadu, India | F70: Ramya Thinakaran | G70: +91 -44-4023-6697 | H70: csv.inmaa@vanguardlogistics.com ramya.thinakaran​@vanguardlogistics.com
B71: Cochin | C71: India | D71: Vanguard Logistics Services | E71: Teepeeyem House, 2nd Floor, Naval Road, Willingdon Island, Cochin - 682 003. Kerala, India. | F71: Mr. Agustin Rockey/Anthony George | G71: 914842666258 | H71: ops.incok@vanguardlogistics.com augustine.rockey​@vanguardlogistics.com antony.george​@vanguardlogistics.com
B72: Coimbatore | C72: India | D72: Vanguard Logistics Services | E72: No. 34 B, Plot No.9 Muniasamypuram 2nd Street Kamaraj Salai,Tuticorn - 628 003, Tamil Nadu, India | F72: Mr. K.Marimuthu | G72: +91 461 422 6410 | H72: ops.intut@vanguardlogistics.com marimuthu.kandasamy​@vanguardlogistics.com
B73: Hyderabad | C73: India | D73: Vanguard Logistics Services | E73: Rama Mansion M No. 1-11-254/11/A Plot No. 4, Situated, Begumpet Hyderabad, India 500 016 | F73: Karthik Mula | G73: +91 40 27765241 | H73: Karthik.Mula​@vanguardlogistics.com
B74: Mumbai | C74: India | D74: Vanguard Logistics Services | E74: The Summit Business Bay M-001 Mezzanine Floor Andheri Kurla Rd Andheri (East), Mumbai 400 093 Maharashtra, India | F74: Sachin Parnerkar | G74: +91 22 4908 5000 | H74: ops.inbom@vanguardlogistics.com sachin.parnerkar​@vanguardlogistics.com
B75: New Delhi | C75: India | D75: Vanguard Logistics Services | E75: B-6/8, 1st Floor, Okhla Industrial Area, Phase-II, New Delhi - 110 020. India. | F75: Rajesh Dogra | G75: +91-11-30679603 | H75: ops.indel@vanguardlogistics.com
B76: Nhava Sheva | C76: India | D76: Vanguard Logistics Services | E76: The Summit Business Bay M-001 Mezzanine Floor Andheri Kurla Rd Andheri (East), Mumbai 400 093 Maharashtra, India | F76: Sachin Parnerkar | G76: +91 22 4908 5000 | H76: ops.inbom@vanguardlogistics.com sachin.parnerkar​@vanguardlogistics.com
B77: Tuticorin | C77: India | D77: Vanguard Logistics Services | E77: No. 34 B, Plot No.9 Muniasamypuram 2nd Street Kamaraj Salai,Tuticorn - 628 003, Tamil Nadu, India | F77: Mr. K.Marimuthu | G77: +91 461 422 6410 | H77: ops.intut@vanguardlogistics.com marimuthu.kandasamy​@vanguardlogistics.com
B78: Belawan | C78: Indonesia | D78: Vanguard Logistics Services Indonesia | E78: Gedung Bank Mandiri 4th Floor Jl. Imam Bonjol No 7, Medan 20112 Indonesia | F78: Ria MELATI | G78: +62 61 4148194 | H78: Blw_export@vanguardlogistics.com ria.melati​@vanguardlogistics.com
B79: Jakarta | C79: Indonesia | D79: Vanguard Logistics Services Indonesia | E79: Hayam Wuruk Plaza Tower, 7th Floor, Suite AB Jl. Hayam Wuruk No 108 Jakarta 11160 Indonesia | F79: Tri SURYANDARI | G79: +62 21 6280748 | H79: jkt_export@vanguardlogistics.com tri.suryandari​@vanguardlogistics.com
B80: Semarang | C80: Indonesia | D80: Vanguard Logistics Services Indonesia | E80: Gedung Griya Bina Artha 3rd Floor Jl Pemuda No. 142, Semarang 50132, Central Java, Indonesia | F80: Emi Sumiarsih | G80: +62 24 352 1886 | H80: Srg_export@vanguardlogistics.com emi.sumiarsih​@vanguardlogistics.com
B81: Surabaya | C81: Indonesia | D81: Vanguard Logistics Services Indonesia | E81: Sinar Mas land Plaza 6th Floor Room 6071 Jl. Pemuda No 60-70 Surabaya 60271, Indonesia | F81: Hanysa Agung | G81: +62 31 5347658 | H81: Sub_export@vanguardlogistics.com hanysa.agung​@vanguardlogistics.com
B82: Dublin | C82: Ireland | D82: Vanguard Logistics | E82: Vanguard Logistics Station House - Station Road Maldon, Essex, United Kingdom CM9 4 LQ | F82: Hannah Symons | G82: +44 16 2187 9200 | H82: hannah.symons@vanguardlogistics.com; ukexpcsu@vanguardlogistics.com
B83: Haifa | C83: Israel | D83: Joint Transport International Services Ltd | E83: Shtibel 4, Tel Aviv | F83: Adi Shwartz | G83: +972-3-6384689 | H83: Export@jti.co.il
... B135: Ho Chi Minh | C135: Vietnam | D135: Vanguard Logistics Services | E135: 5FL, Ha Do Building, No. 02 Hong Ha Street Ward 02, Tan Binh District, Ho Chi Minh City, Viet Nam | F135: Ms Trung Nguyen | G135: (84) 8 3845 9690 | H135: trung.nguyen@vanguardlogistics.com.vn,

Sheet Origin
A1: Aberdeen
A2: Ahmedabad
A3: Antwerp
A4: Atlanta
A5: Auckland
A6: Baltimore
A7: Bangalore
A8: Bangkok
A9: Barcelona
A10: Belawan
A11: Bilbao
A12: Birmingham
... A124: Zhuhai

Sheet Tariff
E1: National Import Tariff | Z1: Vanguard Logistics Import LCL Tariff
E4: Wholesale LCL Tariff
B7: POA-POD-VIA Port | C7: POA-POD | D7: POD-VIA Port | E7: Region | F7: Country | G7: Origin Port | H7: Destination Port | I7: concatenate | J7: Port Code | K7: VIA Port | L7: VIA Country | M7: Service Type | N7: CFS / Gateway | O7: Currency | P7: Rate per cbm | Q7: Rate per tonne | R7: Minimum Charge | S7: GRI per w/m | T7: PSS per w/m | U7: IMO2020 per w/m | V7: BAF/EFS per w/m | W7: ETS per w/m | X7: Transit Time | Y7: Frequency | Z7: Validity | AA7: Conditions
B8: =G8&H8&K8 -> ChittagongSydneySingapore | C8: =G8&H8 -> ChittagongSydney | D8: =H8&K8 -> SydneySingapore | E8: Indian Sub-Continent | F8: Bangladesh | G8: Chittagong | H8: Sydney | I8: ChittagongSydneyTranship | J8: BDCGP | K8: Singapore | L8: Singapore | M8: Tranship | N8: Singapore | O8: USD | P8: 149 | Q8: 149 | R8: 149 | S8: N/A | T8: N/A | U8: 0 | V8: 16 | W8: N/A | X8: 31 | Y8: Weekly | Z8: 46265 | AA8: Subject to applicable GRI, PSS, EFS
B9: =G9&H9&K9 -> ChittagongMelbourneSingapore | C9: =G9&H9 -> ChittagongMelbourne | D9: =H9&K9 -> MelbourneSingapore | E9: Indian Sub-Continent | F9: Bangladesh | G9: Chittagong | H9: Melbourne | I9: ChittagongMelbourneTranship | J9: BDCGP | K9: Singapore | L9: Singapore | M9: Tranship | N9: Singapore | O9: USD | P9: 139 | Q9: 139 | R9: 139 | S9: N/A | T9: N/A | U9: 0 | V9: 16 | W9: N/A | X9: 27 | Y9: Weekly | Z9: 46265 | AA9: Subject to applicable GRI, PSS, EFS
B10: =G10&H10&K10 -> ChittagongFremantleSingapore | C10: =G10&H10 -> ChittagongFremantle | D10: =H10&K10 -> FremantleSingapore | E10: Indian Sub-Continent | F10: Bangladesh | G10: Chittagong | H10: Fremantle | I10: ChittagongFremantleTranship | J10: BDCGP | K10: Singapore | L10: Singapore | M10: Tranship | N10: Singapore | O10: USD | P10: 149 | Q10: 149 | R10: 149 | S10: N/A | T10: N/A | U10: 0 | V10: 16 | W10: N/A | X10: 26 | Y10: Weekly | Z10: 46265 | AA10: Subject to applicable GRI, PSS, EFS
B11: =G11&H11&K11 -> ChittagongBrisbaneSingapore | C11: =G11&H11 -> ChittagongBrisbane | D11: =H11&K11 -> BrisbaneSingapore | E11: Indian Sub-Continent | F11: Bangladesh | G11: Chittagong | H11: Brisbane | I11: ChittagongBrisbaneTranship | J11: BDCGP | K11: Singapore | L11: Singapore | M11: Tranship | N11: Singapore | O11: USD | P11: 139 | Q11: 139 | R11: 139 | S11: N/A | T11: N/A | U11: 0 | V11: 16 | W11: N/A | X11: 27 | Y11: Weekly | Z11: 46265 | AA11: Subject to applicable GRI, PSS, EFS
B12: =G12&H12&K12 -> ChittagongAdelaideSingapore | C12: =G12&H12 -> ChittagongAdelaide | D12: =H12&K12 -> AdelaideSingapore | E12: Indian Sub-Continent | F12: Bangladesh | G12: Chittagong | H12: Adelaide | I12: ChittagongAdelaideTranship | J12: BDCGP | K12: Singapore | L12: Singapore | M12: Tranship | N12: Singapore | O12: USD | P12: 139 | Q12: 139 | R12: 139 | S12: N/A | T12: N/A | U12: 0 | V12: 16 | W12: N/A | X12: 36 | Y12: Weekly | Z12: 46265 | AA12: Subject to applicable GRI, PSS, EFS
B13: =G13&H13&K13 -> AntwerpSydneySingapore | C13: =G13&H13 -> AntwerpSydney | D13: =H13&K13 -> SydneySingapore | E13: Europe | F13: Belgium | G13: Antwerp | H13: Sydney | I13: AntwerpSydneyTranship | J13: BEANR | K13: Singapore | L13: Singapore | M13: Tranship | N13: Singapore | O13: USD | P13: 142 | Q13: 142 | R13: 142 | S13: N/A | T13: N/A | U13: 0 | V13: 16 | W13: 4.5 | X13: 56 | Y13: Weekly | Z13: 46265 | AA13: Subject to applicable GRI, PSS, EFS;Subject to BMSB Treatment conditions
B14: =G14&H14&K14 -> AntwerpMelbourneSingapore | C14: =G14&H14 -> AntwerpMelbourne | D14: =H14&K14 -> MelbourneSingapore | E14: Europe | F14: Belgium | G14: Antwerp | H14: Melbourne | I14: AntwerpMelbourneTranship | J14: BEANR | K14: Singapore | L14: Singapore | M14: Tranship | N14: Singapore | O14: USD | P14: 142 | Q14: 142 | R14: 142 | S14: N/A | T14: N/A | U14: 0 | V14: 16 | W14: 4.5 | X14: 52 | Y14: Weekly | Z14: 46265 | AA14: Subject to applicable GRI, PSS, EFS;Subject to BMSB Treatment conditions
B15: =G15&H15&K15 -> AntwerpFremantleSingapore | C15: =G15&H15 -> AntwerpFremantle | D15: =H15&K15 -> FremantleSingapore | E15: Europe | F15: Belgium | G15: Antwerp | H15: Fremantle | I15: AntwerpFremantleTranship | J15: BEANR | K15: Singapore | L15: Singapore | M15: Tranship | N15: Singapore | O15: USD | P15: 79 | Q15: 79 | R15: 79 | S15: N/A | T15: N/A | U15: 0 | V15: 16 | W15: 4.5 | X15: 51 | Y15: Weekly | Z15: 46265 | AA15: Subject to applicable GRI, PSS, EFS;Subject to BMSB Treatment conditions
B16: =G16&H16&K16 -> AntwerpBrisbaneSingapore | C16: =G16&H16 -> AntwerpBrisbane | D16: =H16&K16 -> BrisbaneSingapore | E16: Europe | F16: Belgium | G16: Antwerp | H16: Brisbane | I16: AntwerpBrisbaneTranship | J16: BEANR | K16: Singapore | L16: Singapore | M16: Tranship | N16: Singapore | O16: USD | P16: 138 | Q16: 138 | R16: 138 | S16: N/A | T16: N/A | U16: 0 | V16: 16 | W16: 4.5 | X16: 52 | Y16: Weekly | Z16: 46265 | AA16: Subject to applicable GRI, PSS, EFS;Subject to BMSB Treatment conditions
B17: =G17&H17&K17 -> AntwerpAdelaideSingapore | C17: =G17&H17 -> AntwerpAdelaide | D17: =H17&K17 -> AdelaideSingapore | E17: Europe | F17: Belgium | G17: Antwerp | H17: Adelaide | I17: AntwerpAdelaideTranship | J17: BEANR | K17: Singapore | L17: Singapore | M17: Tranship | N17: Singapore | O17: USD | P17: 138 | Q17: 138 | R17: 138 | S17: N/A | T17: N/A | U17: 0 | V17: 16 | W17: 4.5 | X17: 61 | Y17: Weekly | Z17: 46265 | AA17: Subject to applicable GRI, PSS, EFS;Subject to BMSB Treatment conditions
B18: =G18&H18&K18 -> SantosSydneySingapore | C18: =G18&H18 -> SantosSydney | D18: =H18&K18 -> SydneySingapore | E18: South America | F18: Brazil | G18: Santos | H18: Sydney | I18: SantosSydneyTranship | J18: BRSSZ | K18: Singapore | L18: Singapore | M18: Tranship | N18: Singapore | O18: USD | P18: 134 | Q18: 134 | R18: 134 | S18: N/A | T18: N/A | U18: 0 | V18: 16 | W18: N/A | X18: 56 | Y18: Weekly | Z18: 46265 | AA18: Subject to applicable GRI, PSS, EFS
B19: =G19&H19&K19 -> SantosMelbourneSingapore | C19: =G19&H19 -> SantosMelbourne | D19: =H19&K19 -> MelbourneSingapore | E19: South America | F19: Brazil | G19: Santos | H19: Melbourne | I19: SantosMelbourneTranship | J19: BRSSZ | K19: Singapore | L19: Singapore | M19: Tranship | N19: Singapore | O19: USD | P19: 134 | Q19: 134 | R19: 134 | S19: N/A | T19: N/A | U19: 0 | V19: 16 | W19: N/A | X19: 52 | Y19: Weekly | Z19: 46265 | AA19: Subject to applicable GRI, PSS, EFS
B20: =G20&H20&K20 -> SantosFremantleSingapore | C20: =G20&H20 -> SantosFremantle | D20: =H20&K20 -> FremantleSingapore | E20: South America | F20: Brazil | G20: Santos | H20: Fremantle | I20: SantosFremantleTranship | J20: BRSSZ | K20: Singapore | L20: Singapore | M20: Tranship | N20: Singapore | O20: USD | P20: 144 | Q20: 144 | R20: 144 | S20: N/A | T20: N/A | U20: 0 | V20: 16 | W20: N/A | X20: 51 | Y20: Weekly | Z20: 46265 | AA20: Subject to applicable GRI, PSS, EFS
B21: =G21&H21&K21 -> SantosBrisbaneSingapore | C21: =G21&H21 -> SantosBrisbane | D21: =H21&K21 -> BrisbaneSingapore | E21: South America | F21: Brazil | G21: Santos | H21: Brisbane | I21: SantosBrisbaneTranship | J21: BRSSZ | K21: Singapore | L21: Singapore | M21: Tranship | N21: Singapore | O21: USD | P21: 134 | Q21: 134 | R21: 134 | S21: N/A | T21: N/A | U21: 0 | V21: 16 | W21: N/A | X21: 52 | Y21: Weekly | Z21: 46265 | AA21: Subject to applicable GRI, PSS, EFS
B22: =G22&H22&K22 -> SantosAdelaideSingapore | C22: =G22&H22 -> SantosAdelaide | D22: =H22&K22 -> AdelaideSingapore | E22: South America | F22: Brazil | G22: Santos | H22: Adelaide | I22: SantosAdelaideTranship | J22: BRSSZ | K22: Singapore | L22: Singapore | M22: Tranship | N22: Singapore | O22: USD | P22: 134 | Q22: 134 | R22: 134 | S22: N/A | T22: N/A | U22: 0 | V22: 16 | W22: N/A | X22: 61 | Y22: Weekly | Z22: 46265 | AA22: Subject to applicable GRI, PSS, EFS
B23: =G23&H23&K23 -> Phnom PenhSydneySingapore | C23: =G23&H23 -> Phnom PenhSydney | D23: =H23&K23 -> SydneySingapore | E23: Asia | F23: Cambodia | G23: Phnom Penh | H23: Sydney | I23: Phnom PenhSydneyTranship | J23: KHPNH | K23: Singapore | L23: Singapore | M23: Tranship | N23: Singapore | O23: USD | P23: 138 | Q23: 138 | R23: 138 | S23: N/A | T23: N/A | U23: 3 | V23: 16 | W23: N/A | X23: 29 | Y23: Weekly | Z23: 46265 | AA23: Subject to applicable GRI, PSS, EFS
B24: =G24&H24&K24 -> Phnom PenhMelbourneSingapore | C24: =G24&H24 -> Phnom PenhMelbourne | D24: =H24&K24 -> MelbourneSingapore | E24: Asia | F24: Cambodia | G24: Phnom Penh | H24: Melbourne | I24: Phnom PenhMelbourneTranship | J24: KHPNH | K24: Singapore | L24: Singapore | M24: Tranship | N24: Singapore | O24: USD | P24: 128 | Q24: 128 | R24: 128 | S24: N/A | T24: N/A | U24: 3 | V24: 16 | W24: N/A | X24: 25 | Y24: Weekly | Z24: 46265 | AA24: Subject to applicable GRI, PSS, EFS
B25: =G25&H25&K25 -> Phnom PenhFremantleSingapore | C25: =G25&H25 -> Phnom PenhFremantle | D25: =H25&K25 -> FremantleSingapore | E25: Asia | F25: Cambodia | G25: Phnom Penh | H25: Fremantle | I25: Phnom PenhFremantleTranship | J25: KHPNH | K25: Singapore | L25: Singapore | M25: Tranship | N25: Singapore | O25: USD | P25: 138 | Q25: 138 | R25: 138 | S25: N/A | T25: N/A | U25: 3 | V25: 16 | W25: N/A | X25: 24 | Y25: Weekly | Z25: 46265 | AA25: Subject to applicable GRI, PSS, EFS
B26: =G26&H26&K26 -> Phnom PenhBrisbaneSingapore | C26: =G26&H26 -> Phnom PenhBrisbane | D26: =H26&K26 -> BrisbaneSingapore | E26: Asia | F26: Cambodia | G26: Phnom Penh | H26: Brisbane | I26: Phnom PenhBrisbaneTranship | J26: KHPNH | K26: Singapore | L26: Singapore | M26: Tranship | N26: Singapore | O26: USD | P26: 128 | Q26: 128 | R26: 128 | S26: N/A | T26: N/A | U26: 3 | V26: 16 | W26: N/A | X26: 25 | Y26: Weekly | Z26: 46265 | AA26: Subject to applicable GRI, PSS, EFS
B27: =G27&H27&K27 -> Phnom PenhAdelaideSingapore | C27: =G27&H27 -> Phnom PenhAdelaide | D27: =H27&K27 -> AdelaideSingapore | E27: Asia | F27: Cambodia | G27: Phnom Penh | H27: Adelaide | I27: Phnom PenhAdelaideTranship | J27: KHPNH | K27: Singapore | L27: Singapore | M27: Tranship | N27: Singapore | O27: USD | P27: 128 | Q27: 128 | R27: 128 | S27: N/A | T27: N/A | U27: 3 | V27: 16 | W27: N/A | X27: 34 | Y27: Weekly | Z27: 46265 | AA27: Subject to applicable GRI, PSS, EFS
B28: =G28&H28&K28 -> SihanoukvilleSydneySingapore | C28: =G28&H28 -> SihanoukvilleSydney | D28: =H28&K28 -> SydneySingapore | E28: Asia | F28: Cambodia | G28: Sihanoukville | H28: Sydney | I28: SihanoukvilleSydneyTranship | J28: KHKOS | K28: Singapore | L28: Singapore | M28: Tranship | N28: Singapore | O28: USD | P28: 138 | Q28: 138 | R28: 138 | S28: N/A | T28: N/A | U28: 3 | V28: 16 | W28: N/A | X28: 29 | Y28: Weekly | Z28: 46265 | AA28: Subject to applicable GRI, PSS, EFS
B29: =G29&H29&K29 -> SihanoukvilleMelbourneSingapore | C29: =G29&H29 -> SihanoukvilleMelbourne | D29: =H29&K29 -> MelbourneSingapore | E29: Asia | F29: Cambodia | G29: Sihanoukville | H29: Melbourne | I29: SihanoukvilleMelbourneTranship | J29: KHKOS | K29: Singapore | L29: Singapore | M29: Tranship | N29: Singapore | O29: USD | P29: 128 | Q29: 128 | R29: 128 | S29: N/A | T29: N/A | U29: 3 | V29: 16 | W29: N/A | X29: 25 | Y29: Weekly | Z29: 46265 | AA29: Subject to applicable GRI, PSS, EFS
... B123: =G123&H123&K123 -> ZhuhaiAdelaideShenzhen | C123: =G123&H123 -> ZhuhaiAdelaide | D123: =H123&K123 -> AdelaideShenzhen | E123: Asia | F123: China | G123: Zhuhai | H123: Adelaide | I123: ZhuhaiAdelaideGateway | J123: CNZUH | K123: Shenzhen | L123: China | M123: Gateway | N123: Shenzhen | O123: USD | P123: 69 | Q123: 138 | R123: 69 | S123: N/A | T123: N/A | U123: 3 | V123: 10 | W123: N/A | X123: 32 | Y123: Weekly | Z123: 46265 | AA123: Subject to applicable GRI, PSS, EFS
B124: =G124&H124&K124 -> AarhusSydneySingapore | C124: =G124&H124 -> AarhusSydney | D124: =H124&K124 -> SydneySingapore | E124: Europe | F124: Denmark | G124: Aarhus | H124: Sydney | I124: AarhusSydneyTranship | J124: DKCPH | K124: Singapore | L124: Singapore | M124: Tranship | N124: Singapore | O124: - | P124: On Application | Q124: - | R124: - | S124: - | T124: - | U124: - | V124: - | W124: - | X124: - | Y124: - | Z124: - | AA124: -
B125: =G125&H125&K125 -> AarhusMelbourneSingapore | C125: =G125&H125 -> AarhusMelbourne | D125: =H125&K125 -> MelbourneSingapore | E125: Europe | F125: Denmark | G125: Aarhus | H125: Melbourne | I125: AarhusMelbourneTranship | J125: DKCPH | K125: Singapore | L125: Singapore | M125: Tranship | N125: Singapore | O125: - | P125: On Application | Q125: - | R125: - | S125: - | T125: - | U125: - | V125: - | W125: - | X125: - | Y125: - | Z125: - | AA125: -
B126: =G126&H126&K126 -> AarhusFremantleSingapore | C126: =G126&H126 -> AarhusFremantle | D126: =H126&K126 -> FremantleSingapore | E126: Europe | F126: Denmark | G126: Aarhus | H126: Fremantle | I126: AarhusFremantleTranship | J126: DKCPH | K126: Singapore | L126: Singapore | M126: Tranship | N126: Singapore | O126: - | P126: On Application | Q126: - | R126: - | S126: - | T126: - | U126: - | V126: - | W126: - | X126: - | Y126: - | Z126: - | AA126: -
B127: =G127&H127&K127 -> AarhusBrisbaneSingapore | C127: =G127&H127 -> AarhusBrisbane | D127: =H127&K127 -> BrisbaneSingapore | E127: Europe | F127: Denmark | G127: Aarhus | H127: Brisbane | I127: AarhusBrisbaneTranship | J127: DKCPH | K127: Singapore | L127: Singapore | M127: Tranship | N127: Singapore | O127: - | P127: On Application | Q127: - | R127: - | S127: - | T127: - | U127: - | V127: - | W127: - | X127: - | Y127: - | Z127: - | AA127: -
B128: =G128&H128&K128 -> AarhusAdelaideSingapore | C128: =G128&H128 -> AarhusAdelaide | D128: =H128&K128 -> AdelaideSingapore | E128: Europe | F128: Denmark | G128: Aarhus | H128: Adelaide | I128: AarhusAdelaideTranship | J128: DKCPH | K128: Singapore | L128: Singapore | M128: Tranship | N128: Singapore | O128: - | P128: On Application | Q128: - | R128: - | S128: - | T128: - | U128: - | V128: - | W128: - | X128: - | Y128: - | Z128: - | AA128: -
B129: =G129&H129&K129 -> CopenhagenSydneySingapore | C129: =G129&H129 -> CopenhagenSydney | D129: =H129&K129 -> SydneySingapore | E129: Europe | F129: Denmark | G129: Copenhagen | H129: Sydney | I129: CopenhagenSydneyTranship | J129: DKCPH | K129: Singapore | L129: Singapore | M129: Tranship | N129: Singapore | O129: - | P129: On Application | Q129: - | R129: - | S129: - | T129: - | U129: - | V129: - | W129: - | X129: - | Y129: - | Z129: - | AA129: -
B130: =G130&H130&K130 -> CopenhagenMelbourneSingapore | C130: =G130&H130 -> CopenhagenMelbourne | D130: =H130&K130 -> MelbourneSingapore | E130: Europe | F130: Denmark | G130: Copenhagen | H130: Melbourne | I130: CopenhagenMelbourneTranship | J130: DKCPH | K130: Singapore | L130: Singapore | M130: Tranship | N130: Singapore | O130: - | P130: On Application | Q130: - | R130: - | S130: - | T130: - | U130: - | V130: - | W130: - | X130: - | Y130: - | Z130: - | AA130: -
B131: =G131&H131&K131 -> CopenhagenFremantleSingapore | C131: =G131&H131 -> CopenhagenFremantle | D131: =H131&K131 -> FremantleSingapore | E131: Europe | F131: Denmark | G131: Copenhagen | H131: Fremantle | I131: CopenhagenFremantleTranship | J131: DKCPH | K131: Singapore | L131: Singapore | M131: Tranship | N131: Singapore | O131: - | P131: On Application | Q131: - | R131: - | S131: - | T131: - | U131: - | V131: - | W131: - | X131: - | Y131: - | Z131: - | AA131: -
B132: =G132&H132&K132 -> CopenhagenBrisbaneSingapore | C132: =G132&H132 -> CopenhagenBrisbane | D132: =H132&K132 -> BrisbaneSingapore | E132: Europe | F132: Denmark | G132: Copenhagen | H132: Brisbane | I132: CopenhagenBrisbaneTranship | J132: DKCPH | K132: Singapore | L132: Singapore | M132: Tranship | N132: Singapore | O132: - | P132: On Application | Q132: - | R132: - | S132: - | T132: - | U132: - | V132: - | W132: - | X132: - | Y132: - | Z132: - | AA132: -
B133: =G133&H133&K133 -> CopenhagenAdelaideSingapore | C133: =G133&H133 -> CopenhagenAdelaide | D133: =H133&K133 -> AdelaideSingapore | E133: Europe | F133: Denmark | G133: Copenhagen | H133: Adelaide | I133: CopenhagenAdelaideTranship | J133: DKCPH | K133: Singapore | L133: Singapore | M133: Tranship | N133: Singapore | O133: - | P133: On Application | Q133: - | R133: - | S133: - | T133: - | U133: - | V133: - | W133: - | X133: - | Y133: - | Z133: - | AA133: -
B134: =G134&H134&K134 -> HelsinkiSydneySingapore | C134: =G134&H134 -> HelsinkiSydney | D134: =H134&K134 -> SydneySingapore | E134: Europe | F134: Finland | G134: Helsinki | H134: Sydney | I134: HelsinkiSydneyTranship | J134: FIHEL | K134: Singapore | L134: Singapore | M134: Tranship | N134: Singapore | O134: - | P134: On Application | Q134: - | R134: - | S134: - | T134: - | U134: - | V134: - | W134: - | X134: - | Y134: - | Z134: - | AA134: -
B135: =G135&H135&K135 -> HelsinkiMelbourneSingapore | C135: =G135&H135 -> HelsinkiMelbourne | D135: =H135&K135 -> MelbourneSingapore | E135: Europe | F135: Finland | G135: Helsinki | H135: Melbourne | I135: HelsinkiMelbourneTranship | J135: FIHEL | K135: Singapore | L135: Singapore | M135: Tranship | N135: Singapore | O135: - | P135: On Application | Q135: - | R135: - | S135: - | T135: - | U135: - | V135: - | W135: - | X135: - | Y135: - | Z135: - | AA135: -
... B138: =G138&H138&K138 -> HelsinkiAdelaideSingapore | C138: =G138&H138 -> HelsinkiAdelaide | D138: =H138&K138 -> AdelaideSingapore | E138: Europe | F138: Finland | G138: Helsinki | H138: Adelaide | I138: HelsinkiAdelaideTranship | J138: FIHEL | K138: Singapore | L138: Singapore | M138: Tranship | N138: Singapore | O138: - | P138: On Application | Q138: - | R138: - | S138: - | T138: - | U138: - | V138: - | W138: - | X138: - | Y138: - | Z138: - | AA138: -
B139: =G139&H139&K139 -> FosSydneySingapore | C139: =G139&H139 -> FosSydney | D139: =H139&K139 -> SydneySingapore | E139: Europe | F139: France | G139: Fos | H139: Sydney | I139: FosSydneyTranship | J139: FRFOS | K139: Singapore | L139: Singapore | M139: Tranship | N139: Singapore | O139: USD | P139: 141 | Q139: 141 | R139: 141 | S139: N/A | T139: N/A | U139: 0 | V139: 16 | W139: 4.5 | X139: 56 | Y139: Weekly | Z139: 46265 | AA139: Subject to applicable GRI, PSS, EFS;Subject to BMSB Treatment conditions
B140: =G140&H140&K140 -> FosMelbourneSingapore | C140: =G140&H140 -> FosMelbourne | D140: =H140&K140 -> MelbourneSingapore | E140: Europe | F140: France | G140: Fos | H140: Melbourne | I140: FosMelbourneTranship | J140: FRFOS | K140: Singapore | L140: Singapore | M140: Tranship | N140: Singapore | O140: USD | P140: 117 | Q140: 117 | R140: 117 | S140: N/A | T140: N/A | U140: 0 | V140: 16 | W140: 4.5 | X140: 52 | Y140: Weekly | Z140: 46265 | AA140: Subject to applicable GRI, PSS, EFS;Subject to BMSB Treatment conditions
B141: =G141&H141&K141 -> FosFremantleSingapore | C141: =G141&H141 -> FosFremantle | D141: =H141&K141 -> FremantleSingapore | E141: Europe | F141: France | G141: Fos | H141: Fremantle | I141: FosFremantleTranship | J141: FRFOS | K141: Singapore | L141: Singapore | M141: Tranship | N141: Singapore | O141: USD | P141: 125 | Q141: 125 | R141: 125 | S141: N/A | T141: N/A | U141: 0 | V141: 16 | W141: 4.5 | X141: 51 | Y141: Weekly | Z141: 46265 | AA141: Subject to applicable GRI, PSS, EFS;Subject to BMSB Treatment conditions
B142: =G142&H142&K142 -> FosBrisbaneSingapore | C142: =G142&H142 -> FosBrisbane | D142: =H142&K142 -> BrisbaneSingapore | E142: Europe | F142: France | G142: Fos | H142: Brisbane | I142: FosBrisbaneTranship | J142: FRFOS | K142: Singapore | L142: Singapore | M142: Tranship | N142: Singapore | O142: USD | P142: 115 | Q142: 115 | R142: 115 | S142: N/A | T142: N/A | U142: 0 | V142: 16 | W142: 4.5 | X142: 52 | Y142: Weekly | Z142: 46265 | AA142: Subject to applicable GRI, PSS, EFS;Subject to BMSB Treatment conditions
B143: =G143&H143&K143 -> FosAdelaideSingapore | C143: =G143&H143 -> FosAdelaide | D143: =H143&K143 -> AdelaideSingapore | E143: Europe | F143: France | G143: Fos | H143: Adelaide | I143: FosAdelaideTranship | J143: FRFOS | K143: Singapore | L143: Singapore | M143: Tranship | N143: Singapore | O143: USD | P143: 115 | Q143: 115 | R143: 115 | S143: N/A | T143: N/A | U143: 0 | V143: 16 | W143: 4.5 | X143: 61 | Y143: Weekly | Z143: 46265 | AA143: Subject to applicable GRI, PSS, EFS;Subject to BMSB Treatment conditions
B144: =G144&H144&K144 -> Le HavreSydneySingapore | C144: =G144&H144 -> Le HavreSydney | D144: =H144&K144 -> SydneySingapore | E144: Europe | F144: France | G144: Le Havre | H144: Sydney | I144: Le HavreSydneyTranship | J144: FRLEH | K144: Singapore | L144: SIngapore | M144: Tranship | N144: Singapore | O144: USD | P144: 153 | Q144: 153 | R144: 153 | S144: N/A | T144: N/A | U144: 0 | V144: 16 | W144: 4.5 | X144: 56 | Y144: Weekly | Z144: 46265 | AA144: Subject to applicable GRI, PSS, EFS;Subject to BMSB Treatment conditions
B145: =G145&H145&K145 -> Le HavreMelbourneSingapore | C145: =G145&H145 -> Le HavreMelbourne | D145: =H145&K145 -> MelbourneSingapore | E145: Europe | F145: France | G145: Le Havre | H145: Melbourne | I145: Le HavreMelbourneTranship | J145: FRLEH | K145: Singapore | L145: SIngapore | M145: Tranship | N145: Singapore | O145: USD | P145: 153 | Q145: 153 | R145: 153 | S145: N/A | T145: N/A | U145: 0 | V145: 16 | W145: 4.5 | X145: 52 | Y145: Weekly | Z145: 46265 | AA145: Subject to applicable GRI, PSS, EFS;Subject to BMSB Treatment conditions
B146: =G146&H146&K146 -> Le HavreFremantleSingapore | C146: =G146&H146 -> Le HavreFremantle | D146: =H146&K146 -> FremantleSingapore | E146: Europe | F146: France | G146: Le Havre | H146: Fremantle | I146: Le HavreFremantleTranship | J146: FRLEH | K146: Singapore | L146: Singapore | M146: Tranship | N146: Singapore | O146: USD | P146: 139 | Q146: 139 | R146: 139 | S146: N/A | T146: N/A | U146: 0 | V146: 16 | W146: 4.5 | X146: 51 | Y146: Weekly | Z146: 46265 | AA146: Subject to applicable GRI, PSS, EFS;Subject to BMSB Treatment conditions
B147: =G147&H147&K147 -> Le HavreBrisbaneSingapore | C147: =G147&H147 -> Le HavreBrisbane | D147: =H147&K147 -> BrisbaneSingapore | E147: Europe | F147: France | G147: Le Havre | H147: Brisbane | I147: Le HavreBrisbaneTranship | J147: FRLEH | K147: Singapore | L147: Singapore | M147: Tranship | N147: Singapore | O147: USD | P147: 129 | Q147: 129 | R147: 129 | S147: N/A | T147: N/A | U147: 0 | V147: 16 | W147: 4.5 | X147: 52 | Y147: Weekly | Z147: 46265 | AA147: Subject to applicable GRI, PSS, EFS;Subject to BMSB Treatment conditions
B148: =G148&H148&K148 -> Le HavreAdelaideSingapore | C148: =G148&H148 -> Le HavreAdelaide | D148: =H148&K148 -> AdelaideSingapore | E148: Europe | F148: France | G148: Le Havre | H148: Adelaide | I148: Le HavreAdelaideTranship | J148: FRLEH | K148: Singapore | L148: Singapore | M148: Tranship | N148: Singapore | O148: USD | P148: 129 | Q148: 129 | R148: 129 | S148: N/A | T148: N/A | U148: 0 | V148: 16 | W148: 4.5 | X148: 61 | Y148: Weekly | Z148: 46265 | AA148: Subject to applicable GRI, PSS, EFS;Subject to BMSB Treatment conditions
B149: =G149&H149&K149 -> LyonSydneySingapore | C149: =G149&H149 -> LyonSydney | D149: =H149&K149 -> SydneySingapore | E149: Europe | F149: France | G149: Lyon | H149: Sydney | I149: LyonSydneyTranship | J149: FRLIO | K149: Singapore | L149: Singapore | M149: Tranship | N149: Singapore | O149: USD | P149: 144 | Q149: 144 | R149: 144 | S149: N/A | T149: N/A | U149: 0 | V149: 16 | W149: 4.5 | X149: 56 | Y149: Weekly | Z149: 46265 | AA149: Subject to applicable GRI, PSS, EFS;Subject to BMSB Treatment conditions
B150: =G150&H150&K150 -> LyonMelbourneSingapore | C150: =G150&H150 -> LyonMelbourne | D150: =H150&K150 -> MelbourneSingapore | E150: Europe | F150: France | G150: Lyon | H150: Melbourne | I150: LyonMelbourneTranship | J150: FRLIO | K150: Singapore | L150: Singapore | M150: Tranship | N150: Singapore | O150: USD | P150: 115 | Q150: 115 | R150: 115 | S150: N/A | T150: N/A | U150: 0 | V150: 16 | W150: 4.5 | X150: 52 | Y150: Weekly | Z150: 46265 | AA150: Subject to applicable GRI, PSS, EFS;Subject to BMSB Treatment conditions
... B158: =G158&H158&K158 -> HamburgAdelaideSingapore | C158: =G158&H158 -> HamburgAdelaide | D158: =H158&K158 -> AdelaideSingapore | E158: Europe | F158: Germany | G158: Hamburg | H158: Adelaide | I158: HamburgAdelaideTranship | J158: DEHAM | K158: Singapore | L158: Singapore | M158: Tranship | N158: Singapore | O158: USD | P158: 106 | Q158: 106 | R158: 106 | S158: N/A | T158: N/A | U158: 0 | V158: 16 | W158: 4.5 | X158: 61 | Y158: Weekly | Z158: 46265 | AA158: Subject to applicable GRI, PSS, EFS;Subject to BMSB Treatment conditions
B159: =G159&H159&K159 -> Hong KongSydneyHong Kong | C159: =G159&H159 -> Hong KongSydney | D159: =H159&K159 -> SydneyHong Kong | E159: Asia | F159: Hong Kong | G159: Hong Kong | H159: Sydney | I159: Hong KongSydneyDirect | J159: HKHKG | K159: Hong Kong | L159: Hong Kong | M159: Direct | N159: Hong Kong | O159: USD | P159: 54 | Q159: 54 | R159: 54 | S159: N/A | T159: N/A | U159: 3 | V159: 10 | W159: N/A | X159: 25 | Y159: Weekly | Z159: 46265 | AA159: Subject to applicable GRI, PSS, EFS
B160: =G160&H160&K160 -> Hong KongMelbourneHong Kong | C160: =G160&H160 -> Hong KongMelbourne | D160: =H160&K160 -> MelbourneHong Kong | E160: Asia | F160: Hong Kong | G160: Hong Kong | H160: Melbourne | I160: Hong KongMelbourneDirect | J160: HKHKG | K160: Hong Kong | L160: Hong Kong | M160: Direct | N160: Hong Kong | O160: USD | P160: 54 | Q160: 54 | R160: 54 | S160: N/A | T160: N/A | U160: 3 | V160: 10 | W160: N/A | X160: 25 | Y160: Weekly | Z160: 46265 | AA160: Subject to applicable GRI, PSS, EFS
B161: =G161&H161&K161 -> Hong KongFremantleSingapore | C161: =G161&H161 -> Hong KongFremantle | D161: =H161&K161 -> FremantleSingapore | E161: Asia | F161: Hong Kong | G161: Hong Kong | H161: Fremantle | I161: Hong KongFremantleTranship | J161: HKHKG | K161: Singapore | L161: Singapore | M161: Tranship | N161: Hong Kong | O161: USD | P161: 65 | Q161: 65 | R161: 65 | S161: N/A | T161: N/A | U161: 3 | V161: 16 | W161: N/A | X161: 24 | Y161: Weekly | Z161: 46265 | AA161: Subject to applicable GRI, PSS, EFS
B162: =G162&H162&K162 -> Hong KongBrisbaneHong Kong | C162: =G162&H162 -> Hong KongBrisbane | D162: =H162&K162 -> BrisbaneHong Kong | E162: Asia | F162: Hong Kong | G162: Hong Kong | H162: Brisbane | I162: Hong KongBrisbaneDirect | J162: HKHKG | K162: Hong Kong | L162: Hong Kong | M162: Direct | N162: Hong Kong | O162: USD | P162: 54 | Q162: 54 | R162: 54 | S162: N/A | T162: N/A | U162: 3 | V162: 10 | W162: N/A | X162: 25 | Y162: Weekly | Z162: 46265 | AA162: Subject to applicable GRI, PSS, EFS
B163: =G163&H163&K163 -> Hong KongAdelaideSingapore | C163: =G163&H163 -> Hong KongAdelaide | D163: =H163&K163 -> AdelaideSingapore | E163: Asia | F163: Hong Kong | G163: Hong Kong | H163: Adelaide | I163: Hong KongAdelaideTranship | J163: HKHKG | K163: Singapore | L163: Singapore | M163: Tranship | N163: Hong Kong | O163: USD | P163: 65 | Q163: 65 | R163: 65 | S163: N/A | T163: N/A | U163: 3 | V163: 16 | W163: N/A | X163: 34 | Y163: Weekly | Z163: 46265 | AA163: Subject to applicable GRI, PSS, EFS
B164: =G164&H164&K164 -> AhmedabadSydneySingapore | C164: =G164&H164 -> AhmedabadSydney | D164: =H164&K164 -> SydneySingapore | E164: Indian Sub-Continent | F164: India | G164: Ahmedabad | H164: Sydney | I164: AhmedabadSydneyTranship | J164: INAMD | K164: Singapore | L164: Singapore | M164: Tranship | N164: Singapore | O164: USD | P164: 172 | Q164: 172 | R164: 172 | S164: N/A | T164: N/A | U164: 0 | V164: 16 | W164: N/A | X164: 34 | Y164: Weekly | Z164: 46265 | AA164: Subject to applicable GRI, PSS, EFS; Subject to IHC, payable at origin
B165: =G165&H165&K165 -> AhmedabadMelbourneSingapore | C165: =G165&H165 -> AhmedabadMelbourne | D165: =H165&K165 -> MelbourneSingapore | E165: Indian Sub-Continent | F165: India | G165: Ahmedabad | H165: Melbourne | I165: AhmedabadMelbourneTranship | J165: INAMD | K165: Singapore | L165: Singapore | M165: Tranship | N165: Singapore | O165: USD | P165: 164 | Q165: 164 | R165: 164 | S165: N/A | T165: N/A | U165: 0 | V165: 16 | W165: N/A | X165: 30 | Y165: Weekly | Z165: 46265 | AA165: Subject to applicable GRI, PSS, EFS; Subject to IHC, payable at origin
B166: =G166&H166&K166 -> AhmedabadFremantleSingapore | C166: =G166&H166 -> AhmedabadFremantle | D166: =H166&K166 -> FremantleSingapore | E166: Indian Sub-Continent | F166: India | G166: Ahmedabad | H166: Fremantle | I166: AhmedabadFremantleTranship | J166: INAMD | K166: Singapore | L166: Singapore | M166: Tranship | N166: Singapore | O166: USD | P166: 182 | Q166: 182 | R166: 182 | S166: N/A | T166: N/A | U166: 0 | V166: 16 | W166: N/A | X166: 29 | Y166: Weekly | Z166: 46265 | AA166: Subject to applicable GRI, PSS, EFS; Subject to IHC, payable at origin
B167: =G167&H167&K167 -> AhmedabadBrisbaneSingapore | C167: =G167&H167 -> AhmedabadBrisbane | D167: =H167&K167 -> BrisbaneSingapore | E167: Indian Sub-Continent | F167: India | G167: Ahmedabad | H167: Brisbane | I167: AhmedabadBrisbaneTranship | J167: INAMD | K167: Singapore | L167: Singapore | M167: Tranship | N167: Singapore | O167: USD | P167: 172 | Q167: 172 | R167: 172 | S167: N/A | T167: N/A | U167: 0 | V167: 16 | W167: N/A | X167: 30 | Y167: Weekly | Z167: 46265 | AA167: Subject to applicable GRI, PSS, EFS; Subject to IHC, payable at origin
B168: =G168&H168&K168 -> AhmedabadAdelaideSingapore | C168: =G168&H168 -> AhmedabadAdelaide | D168: =H168&K168 -> AdelaideSingapore | E168: Indian Sub-Continent | F168: India | G168: Ahmedabad | H168: Adelaide | I168: AhmedabadAdelaideTranship | J168: INAMD | K168: Singapore | L168: Singapore | M168: Tranship | N168: Singapore | O168: USD | P168: 172 | Q168: 172 | R168: 172 | S168: N/A | T168: N/A | U168: 0 | V168: 16 | W168: N/A | X168: 39 | Y168: Weekly | Z168: 46265 | AA168: Subject to applicable GRI, PSS, EFS; Subject to IHC, payable at origin
B169: =G169&H169&K169 -> BangaloreSydneySingapore | C169: =G169&H169 -> BangaloreSydney | D169: =H169&K169 -> SydneySingapore | E169: Indian Sub-Continent | F169: India | G169: Bangalore | H169: Sydney | I169: BangaloreSydneyTranship | J169: INBLR | K169: Singapore | L169: Singapore | M169: Tranship | N169: Singapore | O169: USD | P169: 146 | Q169: 146 | R169: 146 | S169: N/A | T169: N/A | U169: 0 | V169: 16 | W169: N/A | X169: 36 | Y169: Weekly | Z169: 46265 | AA169: Subject to applicable GRI, PSS, EFS; Subject to IHC, payable at origin
B170: =G170&H170&K170 -> BangaloreMelbourneSingapore | C170: =G170&H170 -> BangaloreMelbourne | D170: =H170&K170 -> MelbourneSingapore | E170: Indian Sub-Continent | F170: India | G170: Bangalore | H170: Melbourne | I170: BangaloreMelbourneTranship | J170: INBLR | K170: Singapore | L170: Singapore | M170: Tranship | N170: Singapore | O170: USD | P170: 148 | Q170: 148 | R170: 148 | S170: N/A | T170: N/A | U170: 0 | V170: 16 | W170: N/A | X170: 32 | Y170: Weekly | Z170: 46265 | AA170: Subject to applicable GRI, PSS, EFS; Subject to IHC, payable at origin
... B235: =G235&H235&K235 -> SurabayaAdelaideSingapore | C235: =G235&H235 -> SurabayaAdelaide | D235: =H235&K235 -> AdelaideSingapore | E235: Asia | F235: Indonesia | G235: Surabaya | H235: Adelaide | I235: SurabayaAdelaideTranship | J235: IDSUB | K235: Singapore | L235: Singapore | M235: Tranship | N235: Singapore | O235: USD | P235: 95 | Q235: 95 | R235: 95 | S235: N/A | T235: N/A | U235: 3 | V235: 9 | W235: N/A | X235: 34 | Y235: Weekly | Z235: 46265 | AA235: Subject to applicable GRI, PSS, EFS
B236: =G236&H236&K236 -> DublinSydneyLondon Gateway Port | C236: =G236&H236 -> DublinSydney | D236: =H236&K236 -> SydneyLondon Gateway Port | E236: Europe | F236: Ireland | G236: Dublin | H236: Sydney | I236: DublinSydneyGateway | J236: IEDUB | K236: London Gateway Port | L236: United Kingdom | M236: Gateway | N236: Manchester | O236: USD | P236: 83 | Q236: 83 | R236: 83 | S236: N/A | T236: N/A | U236: 0 | V236: 6 | W236: 4.5 | X236: 52 | Y236: Weekly | Z236: 46265 | AA236: Subject to applicable GRI, PSS, EFS;Rate applicable for bookings with Origin Agent Vanguard UK only
B237: =G237&H237&K237 -> DublinMelbourneLondon Gateway Port | C237: =G237&H237 -> DublinMelbourne | D237: =H237&K237 -> MelbourneLondon Gateway Port | E237: Europe | F237: Ireland | G237: Dublin | H237: Melbourne | I237: DublinMelbourneGateway | J237: IEDUB | K237: London Gateway Port | L237: United Kingdom | M237: Gateway | N237: Manchester | O237: USD | P237: 83 | Q237: 83 | R237: 83 | S237: N/A | T237: N/A | U237: 0 | V237: 6 | W237: 4.5 | X237: 52 | Y237: Weekly | Z237: 46265 | AA237: Subject to applicable GRI, PSS, EFS;Rate applicable for bookings with Origin Agent Vanguard UK only
B238: =G238&H238&K238 -> DublinFremantleSingapore | C238: =G238&H238 -> DublinFremantle | D238: =H238&K238 -> FremantleSingapore | E238: Europe | F238: Ireland | G238: Dublin | H238: Fremantle | I238: DublinFremantleTranship | J238: IEDUB | K238: Singapore | L238: Singapore | M238: Tranship | N238: Manchester | O238: USD | P238: 129 | Q238: 129 | R238: 129 | S238: N/A | T238: N/A | U238: 0 | V238: 16 | W238: 4.5 | X238: 51 | Y238: Weekly | Z238: 46265 | AA238: Subject to applicable GRI, PSS, EFS;Rate applicable for bookings with Origin Agent Vanguard UK only
B239: =G239&H239&K239 -> DublinBrisbaneSingapore | C239: =G239&H239 -> DublinBrisbane | D239: =H239&K239 -> BrisbaneSingapore | E239: Europe | F239: Ireland | G239: Dublin | H239: Brisbane | I239: DublinBrisbaneTranship | J239: IEDUB | K239: Singapore | L239: Singapore | M239: Tranship | N239: Manchester | O239: USD | P239: 129 | Q239: 129 | R239: 129 | S239: N/A | T239: N/A | U239: 0 | V239: 16 | W239: 4.5 | X239: 52 | Y239: Weekly | Z239: 46265 | AA239: Subject to applicable GRI, PSS, EFS;Rate applicable for bookings with Origin Agent Vanguard UK only
B240: =G240&H240&K240 -> DublinAdelaideSingapore | C240: =G240&H240 -> DublinAdelaide | D240: =H240&K240 -> AdelaideSingapore | E240: Europe | F240: Ireland | G240: Dublin | H240: Adelaide | I240: DublinAdelaideTranship | J240: IEDUB | K240: Singapore | L240: Singapore | M240: Tranship | N240: Manchester | O240: USD | P240: 129 | Q240: 129 | R240: 129 | S240: N/A | T240: N/A | U240: 0 | V240: 16 | W240: 4.5 | X240: 61 | Y240: Weekly | Z240: 46265 | AA240: Subject to applicable GRI, PSS, EFS;Rate applicable for bookings with Origin Agent Vanguard UK only
B241: =G241&H241&K241 -> HaifaSydneySingapore | C241: =G241&H241 -> HaifaSydney | D241: =H241&K241 -> SydneySingapore | E241: Mediterranean | F241: Israel | G241: Haifa | H241: Sydney | I241: HaifaSydneyTranship | J241: ILHFA | K241: Singapore | L241: Singapore | M241: Tranship | N241: Singapore | O241: USD | P241: 217 | Q241: 217 | R241: 217 | S241: N/A | T241: N/A | U241: 0 | V241: 16 | W241: N/A | X241: 101 | Y241: Weekly | Z241: 46265 | AA241: Subject to applicable GRI, PSS, EFS
B242: =G242&H242&K242 -> HaifaMelbourneSingapore | C242: =G242&H242 -> HaifaMelbourne | D242: =H242&K242 -> MelbourneSingapore | E242: Mediterranean | F242: Israel | G242: Haifa | H242: Melbourne | I242: HaifaMelbourneTranship | J242: ILHFA | K242: Singapore | L242: Singapore | M242: Tranship | N242: Singapore | O242: USD | P242: 193 | Q242: 193 | R242: 193 | S242: N/A | T242: N/A | U242: 0 | V242: 16 | W242: N/A | X242: 97 | Y242: Weekly | Z242: 46265 | AA242: Subject to applicable GRI, PSS, EFS
B243: =G243&H243&K243 -> HaifaFremantleSingapore | C243: =G243&H243 -> HaifaFremantle | D243: =H243&K243 -> FremantleSingapore | E243: Mediterranean | F243: Israel | G243: Haifa | H243: Fremantle | I243: HaifaFremantleTranship | J243: ILHFA | K243: Singapore | L243: Singapore | M243: Tranship | N243: Singapore | O243: USD | P243: 203 | Q243: 203 | R243: 203 | S243: N/A | T243: N/A | U243: 0 | V243: 16 | W243: N/A | X243: 96 | Y243: Weekly | Z243: 46265 | AA243: Subject to applicable GRI, PSS, EFS
B244: =G244&H244&K244 -> HaifaBrisbaneSingapore | C244: =G244&H244 -> HaifaBrisbane | D244: =H244&K244 -> BrisbaneSingapore | E244: Mediterranean | F244: Israel | G244: Haifa | H244: Brisbane | I244: HaifaBrisbaneTranship | J244: ILHFA | K244: Singapore | L244: Singapore | M244: Tranship | N244: Singapore | O244: USD | P244: 193 | Q244: 193 | R244: 193 | S244: N/A | T244: N/A | U244: 0 | V244: 16 | W244: N/A | X244: 97 | Y244: Weekly | Z244: 46265 | AA244: Subject to applicable GRI, PSS, EFS
B245: =G245&H245&K245 -> HaifaAdelaideSingapore | C245: =G245&H245 -> HaifaAdelaide | D245: =H245&K245 -> AdelaideSingapore | E245: Mediterranean | F245: Israel | G245: Haifa | H245: Adelaide | I245: HaifaAdelaideTranship | J245: ILHFA | K245: Singapore | L245: Singapore | M245: Tranship | N245: Singapore | O245: USD | P245: 193 | Q245: 193 | R245: 193 | S245: N/A | T245: N/A | U245: 0 | V245: 16 | W245: N/A | X245: 106 | Y245: Weekly | Z245: 46265 | AA245: Subject to applicable GRI, PSS, EFS
B246: =G246&H246&K246 -> MilanSydneyLa Spezia | C246: =G246&H246 -> MilanSydney | D246: =H246&K246 -> SydneyLa Spezia | E246: Mediterranean | F246: Italy | G246: Milan | H246: Sydney | I246: MilanSydneyDirect | J246: ITMIL | K246: La Spezia | L246: Italy | M246: Direct | N246: Milan | O246: USD | P246: 67 | Q246: 67 | R246: 67 | S246: N/A | T246: N/A | U246: 0 | V246: 8 | W246: 4.5 | X246: 50 | Y246: Weekly | Z246: 46265 | AA246: Subject to applicable GRI, PSS, EFS;Subject to BMSB Treatment conditions
B247: =G247&H247&K247 -> MilanSydneySingapore | C247: =G247&H247 -> MilanSydney | D247: =H247&K247 -> SydneySingapore | E247: Mediterranean | F247: Italy | G247: Milan | H247: Sydney | I247: MilanSydneyTranship | J247: ITMIL | K247: Singapore | L247: Singapore | M247: Tranship | N247: Singapore | O247: USD | P247: 104 | Q247: 104 | R247: 104 | S247: N/A | T247: N/A | U247: 0 | V247: 16 | W247: 4.5 | X247: 56 | Y247: Weekly | Z247: 46265 | AA247: Subject to applicable GRI, PSS, EFS;Subject to BMSB Treatment conditions
B248: =G248&H248&K248 -> MilanMelbourneLa Spezia | C248: =G248&H248 -> MilanMelbourne | D248: =H248&K248 -> MelbourneLa Spezia | E248: Mediterranean | F248: Italy | G248: Milan | H248: Melbourne | I248: MilanMelbourneDirect | J248: ITMIL | K248: La Spezia | L248: Italy | M248: Direct | N248: Milan | O248: USD | P248: 67 | Q248: 67 | R248: 67 | S248: N/A | T248: N/A | U248: 0 | V248: 8 | W248: 4.5 | X248: 53 | Y248: Weekly | Z248: 46265 | AA248: Subject to applicable GRI, PSS, EFS;Subject to BMSB Treatment conditions
B249: =G249&H249&K249 -> MilanMelbourneSingapore | C249: =G249&H249 -> MilanMelbourne | D249: =H249&K249 -> MelbourneSingapore | E249: Mediterranean | F249: Italy | G249: Milan | H249: Melbourne | I249: MilanMelbourneTranship | J249: ITMIL | K249: Singapore | L249: Singapore | M249: Tranship | N249: Singapore | O249: USD | P249: 104 | Q249: 104 | R249: 104 | S249: N/A | T249: N/A | U249: 0 | V249: 16 | W249: 4.5 | X249: 52 | Y249: Weekly | Z249: 46265 | AA249: Subject to applicable GRI, PSS, EFS;Subject to BMSB Treatment conditions
B250: =G250&H250&K250 -> MilanFremantleSingapore | C250: =G250&H250 -> MilanFremantle | D250: =H250&K250 -> FremantleSingapore | E250: Mediterranean | F250: Italy | G250: Milan | H250: Fremantle | I250: MilanFremantleTranship | J250: ITMIL | K250: Singapore | L250: Singapore | M250: Tranship | N250: Singapore | O250: USD | P250: 73 | Q250: 73 | R250: 73 | S250: N/A | T250: N/A | U250: 0 | V250: 16 | W250: 4.5 | X250: 51 | Y250: Weekly | Z250: 46265 | AA250: Subject to applicable GRI, PSS, EFS;Subject to BMSB Treatment conditions
B251: =G251&H251&K251 -> MilanBrisbaneSingapore | C251: =G251&H251 -> MilanBrisbane | D251: =H251&K251 -> BrisbaneSingapore | E251: Mediterranean | F251: Italy | G251: Milan | H251: Brisbane | I251: MilanBrisbaneTranship | J251: ITMIL | K251: Singapore | L251: Singapore | M251: Tranship | N251: Singapore | O251: USD | P251: 56 | Q251: 56 | R251: 56 | S251: N/A | T251: N/A | U251: 0 | V251: 16 | W251: 4.5 | X251: 52 | Y251: Weekly | Z251: 46265 | AA251: Subject to applicable GRI, PSS, EFS;Subject to BMSB Treatment conditions
B252: =G252&H252&K252 -> MilanAdelaideSingapore | C252: =G252&H252 -> MilanAdelaide | D252: =H252&K252 -> AdelaideSingapore | E252: Mediterranean | F252: Italy | G252: Milan | H252: Adelaide | I252: MilanAdelaideTranship | J252: ITMIL | K252: Singapore | L252: Singapore | M252: Tranship | N252: Singapore | O252: USD | P252: 96 | Q252: 96 | R252: 96 | S252: N/A | T252: N/A | U252: 0 | V252: 16 | W252: 4.5 | X252: 61 | Y252: Weekly | Z252: 46265 | AA252: Subject to applicable GRI, PSS, EFS;Subject to BMSB Treatment conditions
B253: =G253&H253&K253 -> KobeSydneyKobe | C253: =G253&H253 -> KobeSydney | D253: =H253&K253 -> SydneyKobe | E253: Asia | F253: Japan | G253: Kobe | H253: Sydney | I253: KobeSydneyDirect | J253: JPUKB | K253: Kobe | L253: Japan | M253: Direct | N253: Kobe | O253: USD | P253: 111 | Q253: 111 | R253: 111 | S253: N/A | T253: N/A | U253: 3 | V253: 10 | W253: N/A | X253: 30 | Y253: Weekly | Z253: 46265 | AA253: Subject to applicable GRI, PSS, EFS; Subject to BMSB Treatment conditions
B254: =G254&H254&K254 -> KobeMelbourneKobe | C254: =G254&H254 -> KobeMelbourne | D254: =H254&K254 -> MelbourneKobe | E254: Asia | F254: Japan | G254: Kobe | H254: Melbourne | I254: KobeMelbourneDirect | J254: JPUKB | K254: Kobe | L254: Japan | M254: Direct | N254: Kobe | O254: USD | P254: 111 | Q254: 111 | R254: 111 | S254: N/A | T254: N/A | U254: 3 | V254: 10 | W254: N/A | X254: 30 | Y254: Weekly | Z254: 46265 | AA254: Subject to applicable GRI, PSS, EFS; Subject to BMSB Treatment conditions ;
B255: =G255&H255&K255 -> KobeFremantleSingapore | C255: =G255&H255 -> KobeFremantle | D255: =H255&K255 -> FremantleSingapore | E255: Asia | F255: Japan | G255: Kobe | H255: Fremantle | I255: KobeFremantleTranship | J255: JPUKB | K255: Singapore | L255: Singapore | M255: Tranship | N255: Singapore | O255: USD | P255: 175 | Q255: 175 | R255: 175 | S255: N/A | T255: N/A | U255: 3 | V255: 16 | W255: N/A | X255: 29 | Y255: Weekly | Z255: 46265 | AA255: Subject to applicable GRI, PSS, EFS; Subject to BMSB Treatment conditions
B256: =G256&H256&K256 -> KobeBrisbaneSingapore | C256: =G256&H256 -> KobeBrisbane | D256: =H256&K256 -> BrisbaneSingapore | E256: Asia | F256: Japan | G256: Kobe | H256: Brisbane | I256: KobeBrisbaneTranship | J256: JPUKB | K256: Singapore | L256: Singapore | M256: Tranship | N256: Singapore | O256: USD | P256: 165 | Q256: 165 | R256: 165 | S256: N/A | T256: N/A | U256: 3 | V256: 16 | W256: N/A | X256: 30 | Y256: Weekly | Z256: 46265 | AA256: Subject to applicable GRI, PSS, EFS; Subject to BMSB Treatment conditions
B257: =G257&H257&K257 -> KobeAdelaideSingapore | C257: =G257&H257 -> KobeAdelaide | D257: =H257&K257 -> AdelaideSingapore | E257: Asia | F257: Japan | G257: Kobe | H257: Adelaide | I257: KobeAdelaideTranship | J257: JPUKB | K257: Singapore | L257: Singapore | M257: Tranship | N257: Singapore | O257: USD | P257: 165 | Q257: 165 | R257: 165 | S257: N/A | T257: N/A | U257: 3 | V257: 16 | W257: N/A | X257: 39 | Y257: Weekly | Z257: 46265 | AA257: Subject to applicable GRI, PSS, EFS; Subject to BMSB Treatment conditions
B258: =G258&H258&K258 -> NagoyaSydneyNagoya | C258: =G258&H258 -> NagoyaSydney | D258: =H258&K258 -> SydneyNagoya | E258: Asia | F258: Japan | G258: Nagoya | H258: Sydney | I258: NagoyaSydneyDirect | J258: JPNGO | K258: Nagoya | L258: Japan | M258: Direct | N258: Nagoya | O258: USD | P258: 111 | Q258: 111 | R258: 111 | S258: N/A | T258: N/A | U258: 3 | V258: 10 | W258: N/A | X258: 30 | Y258: Weekly | Z258: 46265 | AA258: Subject to applicable GRI, PSS, EFS; Subject to BMSB Treatment conditions
B259: =G259&H259&K259 -> NagoyaMelbourneNagoya | C259: =G259&H259 -> NagoyaMelbourne | D259: =H259&K259 -> MelbourneNagoya | E259: Asia | F259: Japan | G259: Nagoya | H259: Melbourne | I259: NagoyaMelbourneDirect | J259: JPNGO | K259: Nagoya | L259: Japan | M259: Direct | N259: Nagoya | O259: USD | P259: 111 | Q259: 111 | R259: 111 | S259: N/A | T259: N/A | U259: 3 | V259: 10 | W259: N/A | X259: 30 | Y259: Weekly | Z259: 46265 | AA259: Subject to applicable GRI, PSS, EFS; Subject to BMSB Treatment conditions
B260: =G260&H260&K260 -> NagoyaFremantleSingapore | C260: =G260&H260 -> NagoyaFremantle | D260: =H260&K260 -> FremantleSingapore | E260: Asia | F260: Japan | G260: Nagoya | H260: Fremantle | I260: NagoyaFremantleTranship | J260: JPNGO | K260: Singapore | L260: Singapore | M260: Tranship | N260: Singapore | O260: USD | P260: 175 | Q260: 175 | R260: 175 | S260: N/A | T260: N/A | U260: 3 | V260: 16 | W260: N/A | X260: 29 | Y260: Weekly | Z260: 46265 | AA260: Subject to applicable GRI, PSS, EFS; Subject to BMSB Treatment conditions
B261: =G261&H261&K261 -> NagoyaBrisbaneSingapore | C261: =G261&H261 -> NagoyaBrisbane | D261: =H261&K261 -> BrisbaneSingapore | E261: Asia | F261: Japan | G261: Nagoya | H261: Brisbane | I261: NagoyaBrisbaneTranship | J261: JPNGO | K261: Singapore | L261: Singapore | M261: Tranship | N261: Singapore | O261: USD | P261: 165 | Q261: 165 | R261: 165 | S261: N/A | T261: N/A | U261: 3 | V261: 16 | W261: N/A | X261: 30 | Y261: Weekly | Z261: 46265 | AA261: Subject to applicable GRI, PSS, EFS; Subject to BMSB Treatment conditions
B262: =G262&H262&K262 -> NagoyaAdelaideSingapore | C262: =G262&H262 -> NagoyaAdelaide | D262: =H262&K262 -> AdelaideSingapore | E262: Asia | F262: Japan | G262: Nagoya | H262: Adelaide | I262: NagoyaAdelaideTranship | J262: JPNGO | K262: Singapore | L262: Singapore | M262: Tranship | N262: Singapore | O262: USD | P262: 165 | Q262: 165 | R262: 165 | S262: N/A | T262: N/A | U262: 3 | V262: 16 | W262: N/A | X262: 39 | Y262: Weekly | Z262: 46265 | AA262: Subject to applicable GRI, PSS, EFS; Subject to BMSB Treatment conditions
B263: =G263&H263&K263 -> OsakaSydneyKobe | C263: =G263&H263 -> OsakaSydney | D263: =H263&K263 -> SydneyKobe | E263: Asia | F263: Japan | G263: Osaka | H263: Sydney | I263: OsakaSydneyGateway | J263: JPOSA | K263: Kobe | L263: Japan | M263: Gateway | N263: Kobe | O263: USD | P263: 111 | Q263: 111 | R263: 111 | S263: N/A | T263: N/A | U263: 3 | V263: 10 | W263: N/A | X263: 30 | Y263: Weekly | Z263: 46265 | AA263: Subject to applicable GRI, PSS, EFS; Subject to BMSB Treatment conditions
B264: =G264&H264&K264 -> OsakaMelbourneKobe | C264: =G264&H264 -> OsakaMelbourne | D264: =H264&K264 -> MelbourneKobe | E264: Asia | F264: Japan | G264: Osaka | H264: Melbourne | I264: OsakaMelbourneGateway | J264: JPOSA | K264: Kobe | L264: Japan | M264: Gateway | N264: Kobe | O264: USD | P264: 111 | Q264: 111 | R264: 111 | S264: N/A | T264: N/A | U264: 3 | V264: 10 | W264: N/A | X264: 30 | Y264: Weekly | Z264: 46265 | AA264: Subject to applicable GRI, PSS, EFS; Subject to BMSB Treatment conditions
... B302: =G302&H302&K302 -> ManzanilloAdelaideSingapore | C302: =G302&H302 -> ManzanilloAdelaide | D302: =H302&K302 -> AdelaideSingapore | E302: North America | F302: Mexico | G302: Manzanillo | H302: Adelaide | I302: ManzanilloAdelaideTranship | J302: MXZLO | K302: Singapore | L302: Singapore | M302: Tranship | N302: Singapore | O302: USD | P302: 176 | Q302: 176 | R302: 176 | S302: N/A | T302: N/A | U302: 0 | V302: 16 | W302: N/A | X302: 71 | Y302: Weekly | Z302: 46265 | AA302: Subject to applicable GRI, PSS, EFS
B303: =G303&H303&K303 -> RotterdamSydneySingapore | C303: =G303&H303 -> RotterdamSydney | D303: =H303&K303 -> SydneySingapore | E303: Europe | F303: Netherlands | G303: Rotterdam | H303: Sydney | I303: RotterdamSydneyTranship | J303: NLRTM | K303: Singapore | L303: Singapore | M303: Tranship | N303: Singapore | O303: USD | P303: 177 | Q303: 177 | R303: 177 | S303: N/A | T303: N/A | U303: 0 | V303: 16 | W303: 4.5 | X303: 62 | Y303: Weekly | Z303: 46265 | AA303: Subject to applicable GRI, PSS, EFS;Subject to BMSB Treatment conditions
B304: =G304&H304&K304 -> RotterdamMelbourneSingapore | C304: =G304&H304 -> RotterdamMelbourne | D304: =H304&K304 -> MelbourneSingapore | E304: Europe | F304: Netherlands | G304: Rotterdam | H304: Melbourne | I304: RotterdamMelbourneTranship | J304: NLRTM | K304: Singapore | L304: Singapore | M304: Tranship | N304: Singapore | O304: USD | P304: 177 | Q304: 177 | R304: 177 | S304: N/A | T304: N/A | U304: 0 | V304: 16 | W304: 4.5 | X304: 58 | Y304: Weekly | Z304: 46265 | AA304: Subject to applicable GRI, PSS, EFS;Subject to BMSB Treatment conditions
B305: =G305&H305&K305 -> RotterdamFremantleSingapore | C305: =G305&H305 -> RotterdamFremantle | D305: =H305&K305 -> FremantleSingapore | E305: Europe | F305: Netherlands | G305: Rotterdam | H305: Fremantle | I305: RotterdamFremantleTranship | J305: NLRTM | K305: Singapore | L305: Singapore | M305: Tranship | N305: Singapore | O305: USD | P305: 78 | Q305: 78 | R305: 78 | S305: N/A | T305: N/A | U305: 0 | V305: 16 | W305: 4.5 | X305: 57 | Y305: Weekly | Z305: 46265 | AA305: Subject to applicable GRI, PSS, EFS;Subject to BMSB Treatment conditions
B306: =G306&H306&K306 -> RotterdamBrisbaneSingapore | C306: =G306&H306 -> RotterdamBrisbane | D306: =H306&K306 -> BrisbaneSingapore | E306: Europe | F306: Netherlands | G306: Rotterdam | H306: Brisbane | I306: RotterdamBrisbaneTranship | J306: NLRTM | K306: Singapore | L306: Singapore | M306: Tranship | N306: Singapore | O306: USD | P306: 106 | Q306: 106 | R306: 106 | S306: N/A | T306: N/A | U306: 0 | V306: 16 | W306: 4.5 | X306: 58 | Y306: Weekly | Z306: 46265 | AA306: Subject to applicable GRI, PSS, EFS;Subject to BMSB Treatment conditions
B307: =G307&H307&K307 -> RotterdamAdelaideSingapore | C307: =G307&H307 -> RotterdamAdelaide | D307: =H307&K307 -> AdelaideSingapore | E307: Europe | F307: Netherlands | G307: Rotterdam | H307: Adelaide | I307: RotterdamAdelaideTranship | J307: NLRTM | K307: Singapore | L307: Singapore | M307: Tranship | N307: Singapore | O307: USD | P307: 116 | Q307: 116 | R307: 116 | S307: N/A | T307: N/A | U307: 0 | V307: 16 | W307: 4.5 | X307: 67 | Y307: Weekly | Z307: 46265 | AA307: Subject to applicable GRI, PSS, EFS;Subject to BMSB Treatment conditions
...
